<?xml version="1.0" ?>
<TLFDetectEngine type="TLFDetectEngine" predictor="TLFAverageNNPredictor">
    <ILFObjectDetector type="TSCObjectDetector">
        <TSCObjectDetector base_width="24" base_height="24" object_type="unknown" detector="ILFObjectDetector">
            <ILFScanner type="TLFScanner" ApertureWidth="24" ApertureHeight="24">
                <TLFParameter type="TLFParameter" m_Value="10.000000" m_MaxValue="100.000000" m_MinValue="1.000000" m_Name="step" m_Descr="step space as a percentage of baseline resolution" />
                <TLFParameter type="TLFParameter" m_Value="1.100000" m_MaxValue="2.000000" m_MinValue="1.100000" m_Name="grow" m_Descr="step on the scale" />
                <TLFParameter type="TLFParameter" m_Value="1.000000" m_MaxValue="4.000000" m_MinValue="1.000000" m_Name="MinSize" m_Descr="min size of scanned object in the BaseWidth" />
                <TLFParameter type="TLFParameter" m_Value="50.000000" m_MaxValue="100.000000" m_MinValue="1.000000" m_Name="MaxSize" m_Descr="max size of scanned object in the BaseWidth" />
            </ILFScanner>
            <CSClassificator threshold="2.938373">
                <CSWeak weigth="3.339053" v0="8352" v1="8352" v2="32" v3="32" v4="8224" v5="8352" v6="1048688" v7="112" v8="0" v9="2105344" v10="0" v11="67108864" v12="8226" v13="0" v14="288559543" v15="84082688">
                    <CSFeature sxBase="0" syBase="4" wBase="7" hBase="3" />
                </CSWeak>
                <CSWeak weigth="2.969232" v0="40992" v1="41504" v2="2097160" v3="2107938" v4="43682" v5="43554" v6="8234" v7="43578" v8="0" v9="0" v10="536870952" v11="0" v12="2140714" v13="8736" v14="540223674" v15="130">
                    <CSFeature sxBase="0" syBase="0" wBase="7" hBase="7" />
                </CSWeak>
                <CSWeak weigth="2.938373" v0="134261288" v1="2140840" v2="8226" v3="43554" v4="43560" v5="43552" v6="42" v7="10410" v8="10272" v9="8192" v10="8" v11="0" v12="43554" v13="40960" v14="8362" v15="32">
                    <CSFeature sxBase="3" syBase="3" wBase="6" hBase="6" />
                </CSWeak>
            </CSClassificator>
            <CSClassificator threshold="3.819307">
                <CSWeak weigth="2.553929" v0="0" v1="96" v2="64" v3="4194368" v4="64" v5="4194496" v6="4208" v7="272629872" v8="0" v9="112" v10="285216848" v11="128" v12="269500416" v13="268435648" v14="286355824" v15="268435696">
                    <CSFeature sxBase="1" syBase="0" wBase="4" hBase="6" />
                </CSWeak>
                <CSWeak weigth="1.894307" v0="8288" v1="4203248" v2="4194400" v3="4208" v4="8288" v5="224" v6="112" v7="80" v8="32" v9="15770362" v10="0" v11="0" v12="32" v13="32" v14="4209" v15="112">
                    <CSFeature sxBase="1" syBase="8" wBase="5" hBase="3" />
                </CSWeak>
                <CSWeak weigth="1.974232" v0="67133472" v1="67379296" v2="68026624" v3="167776368" v4="537141362" v5="17039360" v6="67703925" v7="71303200" v8="524288" v9="201334784" v10="84411396" v11="67125760" v12="39" v13="0" v14="21042739" v15="256181252">
                    <CSFeature sxBase="0" syBase="5" wBase="7" hBase="2" />
                </CSWeak>
                <CSWeak weigth="1.950807" v0="242887210" v1="1009957498" v2="1211140650" v3="2097154" v4="887761418" v5="1193423418" v6="4850727" v7="131074" v8="1882849834" v9="1073906234" v10="533250" v11="0" v12="598345267" v13="664578" v14="3408951" v15="262160">
                    <CSFeature sxBase="9" syBase="10" wBase="3" hBase="2" />
                </CSWeak>
                <CSWeak weigth="1.925000" v0="2048" v1="544" v2="0" v3="546" v4="10272" v5="10784" v6="174250" v7="41600" v8="0" v9="32" v10="33556480" v11="0" v12="166402" v13="0" v14="570656810" v15="131072">
                    <CSFeature sxBase="3" syBase="0" wBase="6" hBase="7" />
                </CSWeak>
            </CSClassificator>
            <CSClassificator threshold="4.140650">
                <CSWeak weigth="2.107075" v0="8744" v1="43690" v2="0" v3="32" v4="43176" v5="8416" v6="48" v7="176" v8="0" v9="536870912" v10="32" v11="0" v12="8224" v13="0" v14="1048624" v15="32">
                    <CSFeature sxBase="0" syBase="6" wBase="7" hBase="4" />
                </CSWeak>
                <CSWeak weigth="1.450949" v0="0" v1="8224" v2="0" v3="96" v4="8232" v5="32" v6="112" v7="96" v8="0" v9="0" v10="16777248" v11="16777216" v12="131072" v13="0" v14="2297971" v15="48">
                    <CSFeature sxBase="0" syBase="1" wBase="7" hBase="5" />
                </CSWeak>
                <CSWeak weigth="1.431002" v0="41472" v1="5286128" v2="43520" v3="1081376" v4="8192" v5="1048576" v6="0" v7="0" v8="33563136" v9="1255899903" v10="33562880" v11="33554576" v12="270860320" v13="327877085" v14="512" v15="512">
                    <CSFeature sxBase="4" syBase="12" wBase="3" hBase="3" />
                </CSWeak>
                <CSWeak weigth="1.361370" v0="673327138" v1="543304250" v2="134220288" v3="512" v4="2150245114" v5="8" v6="38" v7="66" v8="2105376" v9="41514" v10="0" v11="0" v12="1139" v13="0" v14="65591" v15="0">
                    <CSFeature sxBase="6" syBase="9" wBase="5" hBase="2" />
                </CSWeak>
                <CSWeak weigth="1.389811" v0="1263274504" v1="1325697568" v2="1741676510" v3="5252005" v4="2266827785" v5="575080976" v6="1700742487" v7="1179976020" v8="4260352" v9="151066386" v10="1442891733" v11="1442845953" v12="268435972" v13="269031968" v14="1296913236" v15="84243780">
                    <CSFeature sxBase="6" syBase="0" wBase="5" hBase="2" />
                </CSWeak>
                <CSWeak weigth="1.348278" v0="134261248" v1="67403776" v2="235440136" v3="134251008" v4="41472" v5="67117056" v6="1149274120" v7="0" v8="34816" v9="168331938" v10="32768" v11="33554440" v12="0" v13="0" v14="0" v15="0">
                    <CSFeature sxBase="9" syBase="12" wBase="3" hBase="3" />
                </CSWeak>
                <CSWeak weigth="1.412803" v0="1932663410" v1="271997690" v2="543339122" v3="36704336" v4="1119506994" v5="3223990794" v6="2363410" v7="262160" v8="2032288296" v9="538081322" v10="268440096" v11="655360" v12="2754398" v13="75498501" v14="3145751" v15="17408">
                    <CSFeature sxBase="8" syBase="8" wBase="3" hBase="2" />
                </CSWeak>
                <CSWeak weigth="1.339402" v0="739270752" v1="1089470960" v2="168544772" v3="1115694608" v4="667288256" v5="3597824128" v6="228655194" v7="2483422240" v8="2686206036" v9="1560081116" v10="307242064" v11="5518514" v12="3590266100" v13="4109809137" v14="186918916" v15="7086272">
                    <CSFeature sxBase="0" syBase="12" wBase="2" hBase="1" />
                </CSWeak>
            </CSClassificator>
            <CSClassificator threshold="4.645184">
                <CSWeak weigth="1.583449" v0="0" v1="16" v2="80" v3="131154" v4="0" v5="192" v6="268435552" v7="240" v8="0" v9="0" v10="256" v11="0" v12="0" v13="128" v14="273698928" v15="268439792">
                    <CSFeature sxBase="1" syBase="1" wBase="4" hBase="6" />
                </CSWeak>
                <CSWeak weigth="1.248723" v0="67117088" v1="8944" v2="67108864" v3="64" v4="242" v5="16777296" v6="67125296" v7="67371088" v8="2097152" v9="67109088" v10="83886080" v11="0" v12="16418" v13="67108864" v14="16842801" v15="1140850688">
                    <CSFeature sxBase="0" syBase="6" wBase="7" hBase="2" />
                </CSWeak>
                <CSWeak weigth="1.239162" v0="136358434" v1="2138656" v2="2390788096" v3="2048" v4="10786" v5="546" v6="1140850698" v7="134225920" v8="537043458" v9="32970" v10="0" v11="32768" v12="131626" v13="0" v14="2" v15="0">
                    <CSFeature sxBase="9" syBase="11" wBase="3" hBase="3" />
                </CSWeak>
                <CSWeak weigth="1.162672" v0="168571452" v1="570426896" v2="117722974" v3="135315715" v4="1711276545" v5="131072" v6="1157697351" v7="1325471748" v8="37748808" v9="16781314" v10="58740407" v11="218237057" v12="72" v13="264" v14="1163943693" v15="252183052">
                    <CSFeature sxBase="1" syBase="1" wBase="6" hBase="2" />
                </CSWeak>
                <CSWeak weigth="1.165686" v0="43042" v1="167813880" v2="34113568" v3="134252628" v4="43688" v5="532514" v6="10485792" v7="8519828" v8="36216864" v9="1003454661" v10="75497472" v11="5263554" v12="16777216" v13="328794317" v14="33556482" v15="5120">
                    <CSFeature sxBase="7" syBase="12" wBase="2" hBase="3" />
                </CSWeak>
                <CSWeak weigth="1.123099" v0="540024944" v1="541094128" v2="368" v3="112" v4="270532720" v5="0" v6="83" v7="0" v8="536870944" v9="5242912" v10="0" v11="0" v12="48" v13="0" v14="16843025" v15="0">
                    <CSFeature sxBase="1" syBase="8" wBase="5" hBase="2" />
                </CSWeak>
                <CSWeak weigth="1.153972" v0="536889376" v1="1882286634" v2="807567520" v3="1089603754" v4="2099298" v5="2234474" v6="268437672" v7="1076887610" v8="2004317543" v9="274792482" v10="2055275538" v11="358813696" v12="1360426357" v13="1363231757" v14="1073890542" v15="1078988874">
                    <CSFeature sxBase="12" syBase="8" wBase="3" hBase="1" />
                </CSWeak>
                <CSWeak weigth="1.164391" v0="405287664" v1="690911480" v2="36969468" v3="33819796" v4="235012416" v5="607468" v6="185337647" v7="167971823" v8="1882198112" v9="2019219152" v10="2603681840" v11="203424768" v12="16844849" v13="33818048" v14="253364296" v15="67109504">
                    <CSFeature sxBase="0" syBase="7" wBase="5" hBase="1" />
                </CSWeak>
                <CSWeak weigth="1.118016" v0="32" v1="114885212" v2="0" v3="1082130448" v4="1073741824" v5="13107276" v6="65616" v7="13631492" v8="79716384" v9="1342111948" v10="33554432" v11="102694993" v12="17104901" v13="797033868" v14="356779265" v15="54591764">
                    <CSFeature sxBase="3" syBase="12" wBase="2" hBase="3" />
                </CSWeak>
                <CSWeak weigth="1.117238" v0="4049795640" v1="322361946" v2="405453312" v3="8540186" v4="305805858" v5="67270738" v6="1949707282" v7="16921618" v8="1479692288" v9="67261143" v10="339771392" v11="1311761" v12="18231843" v13="67245568" v14="342238245" v15="69337348">
                    <CSFeature sxBase="9" syBase="10" wBase="2" hBase="2" />
                </CSWeak>
            </CSClassificator>
            <CSClassificator threshold="5.967517">
                <CSWeak weigth="1.191858" v0="136489506" v1="32" v2="2" v3="0" v4="10922" v5="32" v6="34" v7="65568" v8="10282" v9="0" v10="0" v11="0" v12="2602" v13="0" v14="34" v15="0">
                    <CSFeature sxBase="9" syBase="7" wBase="4" hBase="3" />
                </CSWeak>
                <CSWeak weigth="1.038203" v0="140687408" v1="5394674" v2="688146" v3="35705040" v4="1344466986" v5="268570642" v6="1160466482" v7="8395910" v8="20578400" v9="8405184" v10="308432914" v11="16777424" v12="300093458" v13="81924" v14="665784595" v15="136192">
                    <CSFeature sxBase="8" syBase="9" wBase="2" hBase="3" />
                </CSWeak>
                <CSWeak weigth="1.028315" v0="0" v1="8704" v2="2097152" v3="2" v4="43554" v5="43008" v6="34" v7="10402" v8="0" v9="0" v10="536870952" v11="0" v12="41480" v13="512" v14="35692584" v15="128">
                    <CSFeature sxBase="0" syBase="0" wBase="7" hBase="7" />
                </CSWeak>
                <CSWeak weigth="1.016984" v0="201850922" v1="537657452" v2="223612878" v3="67243080" v4="2560" v5="134218304" v6="17012" v7="1308624978" v8="67634688" v9="2316" v10="218530311" v11="235146249" v12="68161036" v13="134351368" v14="16981779" v15="50465800">
                    <CSFeature sxBase="0" syBase="3" wBase="5" hBase="2" />
                </CSWeak>
                <CSWeak weigth="0.969867" v0="536912384" v1="35954688" v2="1111534080" v3="167806976" v4="537927680" v5="33554528" v6="524288" v7="0" v8="54969536" v9="2342242753" v10="37748740" v11="34668624" v12="34603264" v13="797771200" v14="770" v15="16777984">
                    <CSFeature sxBase="6" syBase="15" wBase="2" hBase="2" />
                </CSWeak>
                <CSWeak weigth="0.960002" v0="1151494720" v1="1416253226" v2="1023019042" v3="1793998888" v4="336686823" v5="3355864682" v6="1347567810" v7="1347572980" v8="1928520118" v9="1148272704" v10="3493208243" v11="1080115280" v12="1071093" v13="1363242373" v14="340082933" v15="1347621905">
                    <CSFeature sxBase="9" syBase="8" wBase="4" hBase="1" />
                </CSWeak>
                <CSWeak weigth="0.987586" v0="35362" v1="8421552" v2="32802" v3="34978" v4="41506" v5="672" v6="2082" v7="210" v8="32800" v9="2290843778" v10="131080" v11="33554464" v12="33314" v13="2097320" v14="139314" v15="48">
                    <CSFeature sxBase="7" syBase="9" wBase="3" hBase="4" />
                </CSWeak>
                <CSWeak weigth="1.026141" v0="1110463072" v1="269013080" v2="288556087" v3="410059807" v4="143679576" v5="579664" v6="67243333" v7="187387823" v8="917533216" v9="610353728" v10="1181747441" v11="179307554" v12="436342788" v13="134351400" v14="185466880" v15="235668994">
                    <CSFeature sxBase="0" syBase="7" wBase="4" hBase="1" />
                </CSWeak>
                <CSWeak weigth="1.016887" v0="511979080" v1="539077472" v2="522743623" v3="1435757409" v4="86999564" v5="203538944" v6="1192200047" v7="1342718337" v8="8693512" v9="2239824928" v10="89655051" v11="101012006" v12="1574151" v13="8446144" v14="256180839" v15="51709699">
                    <CSFeature sxBase="6" syBase="0" wBase="5" hBase="1" />
                </CSWeak>
                <CSWeak weigth="0.994068" v0="543689322" v1="6707226" v2="405356858" v3="561910584" v4="355668008" v5="88951354" v6="1425809412" v7="1415854104" v8="1937131090" v9="302190593" v10="838232147" v11="90326016" v12="1076983253" v13="1376744781" v14="7364770" v15="1346584599">
                    <CSFeature sxBase="12" syBase="6" wBase="3" hBase="1" />
                </CSWeak>
                <CSWeak weigth="1.024419" v0="1949847600" v1="940242540" v2="24908350" v3="213451189" v4="1582088" v5="270595308" v6="320865103" v7="153814447" v8="4037062704" v9="1797406760" v10="418384056" v11="2293920" v12="824202321" v13="539510848" v14="186657173" v15="102767268">
                    <CSFeature sxBase="2" syBase="9" wBase="4" hBase="1" />
                </CSWeak>
                <CSWeak weigth="0.984710" v0="1887074816" v1="1845131354" v2="278005826" v3="67276826" v4="145930874" v5="1393179316" v6="3739922" v7="67502111" v8="3039484498" v9="106598648" v10="606146625" v11="1179700" v12="582644294" v13="156166" v14="656439" v15="2097260">
                    <CSFeature sxBase="8" syBase="9" wBase="2" hBase="2" />
                </CSWeak>
                <CSWeak weigth="0.972598" v0="1048576" v1="38274048" v2="67633168" v3="1" v4="1364328448" v5="83951876" v6="1359290643" v7="196624" v8="1345847296" v9="2061439168" v10="0" v11="470810628" v12="50790657" v13="1456423005" v14="419779846" v15="21299217">
                    <CSFeature sxBase="0" syBase="14" wBase="3" hBase="2" />
                </CSWeak>
                <CSWeak weigth="0.989421" v0="1291846248" v1="721995904" v2="117706543" v3="1949046731" v4="1074070546" v5="272640" v6="1907335943" v7="1164837191" v8="1115818560" v9="2533883914" v10="117607199" v11="218253312" v12="1107298484" v13="1241521168" v14="151674645" v15="252184328">
                    <CSFeature sxBase="3" syBase="0" wBase="5" hBase="2" />
                </CSWeak>
            </CSClassificator>
            <CSClassificator threshold="6.264171">
                <CSWeak weigth="0.957495" v0="8704" v1="33597952" v2="704686592" v3="2717944320" v4="67109376" v5="2048" v6="84197376" v7="0" v8="41984544" v9="2407722667" v10="33595904" v11="184549386" v12="50340352" v13="50364808" v14="33689344" v15="33554944">
                    <CSFeature sxBase="7" syBase="15" wBase="3" hBase="2" />
                </CSWeak>
                <CSWeak weigth="0.961225" v0="1346521122" v1="812533866" v2="1886388394" v3="28966970" v4="1364740490" v5="270744170" v6="10485800" v7="302646447" v8="4117983607" v9="16384" v10="3028209718" v11="1107492864" v12="1359140341" v13="1359086853" v14="1344303140" v15="268638319">
                    <CSFeature sxBase="12" syBase="7" wBase="3" hBase="1" />
                </CSWeak>
                <CSWeak weigth="0.920155" v0="807422496" v1="1428834858" v2="2569150690" v3="1623146538" v4="50419850" v5="2216823470" v6="2158133282" v7="1077578282" v8="2012435827" v9="526338" v10="905126178" v11="607453192" v12="1358986709" v13="1358974213" v14="274866250" v15="276500491">
                    <CSFeature sxBase="12" syBase="9" wBase="3" hBase="1" />
                </CSWeak>
                <CSWeak weigth="0.874213" v0="2138272" v1="704939746" v2="2357231618" v3="168855778" v4="2138144" v5="4194402" v6="18874406" v7="262146" v8="34078944" v9="4220420293" v10="134234112" v11="34604228" v12="2097220" v13="61341896" v14="34217984" v15="260">
                    <CSFeature sxBase="8" syBase="12" wBase="2" hBase="3" />
                </CSWeak>
                <CSWeak weigth="0.903134" v0="55191600" v1="1720344" v2="1143048996" v3="109092904" v4="96485380" v5="671892480" v6="268468800" v7="50465864" v8="2340421656" v9="268468224" v10="42033224" v11="1242106888" v12="152043578" v13="33824845" v14="290027795" v15="252192267">
                    <CSFeature sxBase="1" syBase="2" wBase="3" hBase="2" />
                </CSWeak>
                <CSWeak weigth="0.905611" v0="816863328" v1="825381578" v2="11994303" v3="1761543183" v4="269512768" v5="135282912" v6="1075905807" v7="2100559" v8="808480880" v9="1890738186" v10="943392956" v11="24512687" v12="1917874240" v13="1931624960" v14="185615616" v15="176816654">
                    <CSFeature sxBase="0" syBase="8" wBase="3" hBase="1" />
                </CSWeak>
                <CSWeak weigth="0.874571" v0="64" v1="188941376" v2="67108864" v3="1073741824" v4="512" v5="50335744" v6="67371008" v7="1049088" v8="1191510016" v9="2698970328" v10="262144" v11="38862865" v12="85267488" v13="328143301" v14="50398465" v15="327681">
                    <CSFeature sxBase="1" syBase="12" wBase="3" hBase="3" />
                </CSWeak>
                <CSWeak weigth="0.895283" v0="1409954320" v1="2117849608" v2="836834592" v3="4273940639" v4="11664050" v5="1430060282" v6="7868622" v7="191131887" v8="4243747548" v9="3744210944" v10="1153237056" v11="195953256" v12="326301409" v13="1409288264" v14="20060329" v15="1225395884">
                    <CSFeature sxBase="7" syBase="8" wBase="3" hBase="1" />
                </CSWeak>
                <CSWeak weigth="0.860930" v0="2550139456" v1="271848280" v2="3464661943" v3="1845531670" v4="2550434184" v5="2287245592" v6="706973641" v7="4827290" v8="2181303812" v9="1095051354" v10="2937045646" v11="524294" v12="218104064" v13="276890026" v14="2218298888" v15="32">
                    <CSFeature sxBase="14" syBase="13" wBase="2" hBase="1" />
                </CSWeak>
                <CSWeak weigth="0.888820" v0="3162128" v1="589975620" v2="272564286" v3="150864186" v4="1087402008" v5="2353351360" v6="67371407" v7="1441935" v8="2020898864" v9="945975858" v10="280434738" v11="3605026" v12="4062206048" v13="2020667508" v14="3162112" v15="268828676">
                    <CSFeature sxBase="0" syBase="10" wBase="3" hBase="1" />
                </CSWeak>
                <CSWeak weigth="0.875671" v0="15482944" v1="234400932" v2="3296259088" v3="1164214413" v4="2162163744" v5="1052477600" v6="1080165396" v7="2181365952" v8="3118499008" v9="3424702088" v10="1287702549" v11="1497368848" v12="113428632" v13="1795219374" v14="18549506" v15="319359168">
                    <CSFeature sxBase="8" syBase="15" wBase="1" hBase="2" />
                </CSWeak>
                <CSWeak weigth="0.885187" v0="1521906512" v1="1010196564" v2="369052348" v3="179514406" v4="17844344" v5="136452846" v6="667023" v7="403659919" v8="947003440" v9="879499780" v10="2100431921" v11="35522860" v12="305388768" v13="453134632" v14="321915669" v15="168697602">
                    <CSFeature sxBase="1" syBase="6" wBase="3" hBase="1" />
                </CSWeak>
                <CSWeak weigth="0.888306" v0="2802061384" v1="1778657560" v2="891254735" v3="4143995522" v4="1073741896" v5="536873488" v6="1426342735" v7="491258733" v8="34214400" v9="5767432" v10="117459793" v11="490799368" v12="1081664" v13="201855010" v14="1090522973" v15="1292045832">
                    <CSFeature sxBase="0" syBase="0" wBase="7" hBase="2" />
                </CSWeak>
                <CSWeak weigth="0.885486" v0="1416645136" v1="3594476186" v2="282745344" v3="3874885722" v4="308443764" v5="1610747510" v6="2419195976" v7="1094849184" v8="3889720176" v9="1141844528" v10="285182096" v11="1143210042" v12="1631122901" v13="395970" v14="1148862697" v15="16">
                    <CSFeature sxBase="9" syBase="11" wBase="3" hBase="1" />
                </CSWeak>
                <CSWeak weigth="0.889042" v0="1484978754" v1="5279760" v2="671259138" v3="2483181364" v4="572700706" v5="20482" v6="279053312" v7="8533302" v8="540184576" v9="176787668" v10="1357910592" v11="2101460" v12="271716370" v13="10698960" v14="1079201809" v15="67114065">
                    <CSFeature sxBase="7" syBase="10" wBase="2" hBase="3" />
                </CSWeak>
                <CSWeak weigth="0.894680" v0="4028645952" v1="3728097962" v2="2687552544" v3="4177248298" v4="1313614362" v5="1613169322" v6="560302248" v7="2844938" v8="3509246597" v9="1141162498" v10="3961586176" v11="1078331936" v12="1415643093" v13="273047560" v14="70385870" v15="319160365">
                    <CSFeature sxBase="12" syBase="10" wBase="2" hBase="1" />
                </CSWeak>
                <CSWeak weigth="0.905210" v0="4849664" v1="116152516" v2="2190475584" v3="102401" v4="71565376" v5="354992212" v6="1313586" v7="1091986448" v8="873531392" v9="2412710106" v10="391397377" v11="5046609" v12="1124552784" v13="1034360912" v14="358034256" v15="323420498">
                    <CSFeature sxBase="0" syBase="15" wBase="2" hBase="2" />
                </CSWeak>
            </CSClassificator>
            <CSClassificator threshold="7.371644">
                <CSWeak weigth="0.857878" v0="35360" v1="8421538" v2="2147516416" v3="136316976" v4="546" v5="144" v6="32" v7="16" v8="512" v9="176194178" v10="33554464" v11="134218240" v12="32" v13="8388608" v14="48" v15="112">
                    <CSFeature sxBase="4" syBase="9" wBase="4" hBase="4" />
                </CSWeak>
                <CSWeak weigth="0.875333" v0="0" v1="33554432" v2="1024" v3="4608" v4="0" v5="0" v6="64" v7="0" v8="0" v9="167772160" v10="67109920" v11="4" v12="2048" v13="16777216" v14="288559154" v15="16908290">
                    <CSFeature sxBase="0" syBase="0" wBase="7" hBase="4" />
                </CSWeak>
                <CSWeak weigth="0.793430" v0="1409946146" v1="1860916762" v2="2491303012" v3="1627326090" v4="289073794" v5="682221736" v6="2163343566" v7="204738703" v8="4141147744" v9="3996781452" v10="2048226" v11="1141310692" v12="328103381" v13="352469000" v14="1215312102" v15="16912420">
                    <CSFeature sxBase="8" syBase="8" wBase="3" hBase="1" />
                </CSWeak>
                <CSWeak weigth="0.819766" v0="172009984" v1="8953984" v2="1308666368" v3="595625991" v4="2921505280" v5="827392" v6="562136144" v7="100665344" v8="2327896808" v9="730759374" v10="184549376" v11="218105921" v12="50331680" v13="167772736" v14="33557760" v15="33555200">
                    <CSFeature sxBase="9" syBase="15" wBase="2" hBase="2" />
                </CSWeak>
                <CSWeak weigth="0.786944" v0="1748004944" v1="28872" v2="24248363" v3="9372719" v4="322990176" v5="3322045640" v6="132359" v7="5113247" v8="3002233456" v9="4205500448" v10="707788848" v11="3866670" v12="1881175152" v13="4179798144" v14="322176256" v15="21104900">
                    <CSFeature sxBase="1" syBase="9" wBase="3" hBase="1" />
                </CSWeak>
                <CSWeak weigth="0.823914" v0="69348898" v1="1279159842" v2="1224354402" v3="1760182434" v4="538979872" v5="1208676010" v6="134260962" v7="18875434" v8="1425305696" v9="1141899296" v10="3768590371" v11="67305536" v12="8410485" v13="3073" v14="2310340" v15="69337092">
                    <CSFeature sxBase="9" syBase="10" wBase="4" hBase="1" />
                </CSWeak>
                <CSWeak weigth="0.838372" v0="1074036736" v1="1079017600" v2="2105376" v3="196652" v4="8192" v5="3150016" v6="4" v7="71368704" v8="3227558016" v9="2878324928" v10="50331776" v11="1115362" v12="51380224" v13="92864712" v14="16777744" v15="35717377">
                    <CSFeature sxBase="5" syBase="12" wBase="2" hBase="3" />
                </CSWeak>
                <CSWeak weigth="0.804378" v0="1924549168" v1="3702410830" v2="284050520" v3="1760516010" v4="1817180812" v5="241036492" v6="220485069" v7="70009087" v8="4074299494" v9="1589265408" v10="1257449603" v11="1432961152" v12="10503621" v13="1086850057" v14="3390701752" v15="357187628">
                    <CSFeature sxBase="7" syBase="7" wBase="4" hBase="1" />
                </CSWeak>
                <CSWeak weigth="0.818285" v0="134252544" v1="51662848" v2="3630991460" v3="1107951872" v4="83896320" v5="1564541056" v6="895484947" v7="1342419212" v8="2048" v9="0" v10="65536" v11="0" v12="67108864" v13="16777216" v14="16842752" v15="16777224">
                    <CSFeature sxBase="11" syBase="12" wBase="3" hBase="3" />
                </CSWeak>
                <CSWeak weigth="0.817406" v0="1947236464" v1="2250272876" v2="1077747738" v3="7287870" v4="268456048" v5="2460014804" v6="35849485" v7="1835407" v8="1890744368" v9="4141924392" v10="540016679" v11="35848709" v12="817132656" v13="4084203728" v14="3145796" v15="64">
                    <CSFeature sxBase="1" syBase="10" wBase="3" hBase="1" />
                </CSWeak>
                <CSWeak weigth="0.828045" v0="15246464" v1="820553416" v2="639282970" v3="1753325960" v4="33620514" v5="2700153252" v6="369821192" v7="436469761" v8="80248944" v9="2614611150" v10="67256640" v11="457425166" v12="187138353" v13="579587983" v14="520686862" v15="1191385347">
                    <CSFeature sxBase="6" syBase="18" wBase="2" hBase="1" />
                </CSWeak>
                <CSWeak weigth="0.833667" v0="1476415552" v1="842164288" v2="292356141" v3="1437283087" v4="1343510778" v5="2514520556" v6="679741711" v7="67839167" v8="4178860144" v9="3188342785" v10="645529680" v11="39716872" v12="1480611920" v13="3932209160" v14="256118021" v15="235279362">
                    <CSFeature sxBase="0" syBase="7" wBase="2" hBase="1" />
                </CSWeak>
                <CSWeak weigth="0.836773" v0="1352681994" v1="1417112170" v2="2032287778" v3="4026417442" v4="1426181632" v5="1346503818" v6="1175126208" v7="1349386282" v8="845207430" v9="336492624" v10="572067842" v11="1144014178" v12="335871989" v13="1162222157" v14="74518734" v15="17324297">
                    <CSFeature sxBase="11" syBase="8" wBase="3" hBase="1" />
                </CSWeak>
                <CSWeak weigth="0.813499" v0="532939368" v1="4190407248" v2="802101168" v3="1682055712" v4="2946448916" v5="202376412" v6="1073043325" v7="1125128005" v8="721420800" v9="142871554" v10="256763748" v11="1359479892" v12="18940940" v13="1426063648" v14="1566381685" v15="356584216">
                    <CSFeature sxBase="9" syBase="0" wBase="4" hBase="2" />
                </CSWeak>
                <CSWeak weigth="0.818234" v0="1677746688" v1="1594317322" v2="1376658048" v3="1371412730" v4="31496226" v5="136864482" v6="279851151" v7="50427326" v8="857872914" v9="1797151248" v10="3867217954" v11="86264560" v12="1946346640" v13="134375426" v14="835138811" v15="18612356">
                    <CSFeature sxBase="8" syBase="10" wBase="2" hBase="1" />
                </CSWeak>
                <CSWeak weigth="0.844234" v0="1789555400" v1="303694352" v2="1408516654" v3="1333738815" v4="412568144" v5="1325417314" v6="1342497807" v7="307154158" v8="3595638000" v9="1394806785" v10="1780744721" v11="59910273" v12="1852639844" v13="422381696" v14="51927372" v15="255986182">
                    <CSFeature sxBase="1" syBase="5" wBase="2" hBase="1" />
                </CSWeak>
                <CSWeak weigth="0.824262" v0="2517154456" v1="211850963" v2="1213772008" v3="1220728426" v4="1070148" v5="1163964172" v6="4265135562" v7="239614026" v8="2873152642" v9="568365523" v10="1217715972" v11="270918882" v12="2997037280" v13="227550728" v14="3774894591" v15="388373376">
                    <CSFeature sxBase="10" syBase="5" wBase="1" hBase="1" />
                </CSWeak>
                <CSWeak weigth="0.819272" v0="1380338178" v1="1379599978" v2="3960113418" v3="1542685242" v4="3798220938" v5="69370392" v6="444651530" v7="571605610" v8="2031246100" v9="1363167753" v10="150389401" v11="269754368" v12="398783957" v13="67785" v14="268583132" v15="268566534">
                    <CSFeature sxBase="14" syBase="10" wBase="2" hBase="1" />
                </CSWeak>
                <CSWeak weigth="0.823571" v0="2147518496" v1="25198728" v2="8396960" v3="10488016" v4="2130656" v5="1052880" v6="10639530" v7="16389" v8="2048" v9="2192277632" v10="135232" v11="246" v12="680" v13="1359282244" v14="1280507" v15="4432">
                    <CSFeature sxBase="7" syBase="9" wBase="2" hBase="4" />
                </CSWeak>
                <CSWeak weigth="0.837061" v0="805851168" v1="504058952" v2="95044618" v3="3387906287" v4="269512768" v5="33578176" v6="1409335311" v7="35149039" v8="2138722936" v9="992676864" v10="121242209" v11="36398988" v12="22048920" v13="352864418" v14="574623044" v15="453905944">
                    <CSFeature sxBase="5" syBase="8" wBase="2" hBase="1" />
                </CSWeak>
            </CSClassificator>
            <CSClassificator threshold="7.606995">
                <CSWeak weigth="0.989464" v0="538994720" v1="126818252" v2="318767136" v3="1328524626" v4="197193736" v5="2879080228" v6="286460193" v7="287245325" v8="130039808" v9="2281607493" v10="54794544" v11="319750494" v12="2387306760" v13="1073677668" v14="654319875" v15="50401737">
                    <CSFeature sxBase="0" syBase="12" wBase="1" hBase="3" />
                </CSWeak>
                <CSWeak weigth="0.976316" v0="962087520" v1="1187154174" v2="346240542" v3="2169327893" v4="535453059" v5="3325831680" v6="3679538545" v7="1191853906" v8="2820554068" v9="1140716397" v10="3010439141" v11="3743066491" v12="1297544142" v13="3481734353" v14="1596841779" v15="158799707">
                    <CSFeature sxBase="0" syBase="18" wBase="1" hBase="1" />
                </CSWeak>
                <CSWeak weigth="1.010312" v0="1263987158" v1="2881692669" v2="2673802750" v3="2381403823" v4="3683421800" v5="3908615054" v6="3615420166" v7="2063765627" v8="3136272196" v9="2995396686" v10="1834166264" v11="654586638" v12="279227657" v13="3602014173" v14="66441071" v15="1325417692">
                    <CSFeature sxBase="15" syBase="17" wBase="1" hBase="1" />
                </CSWeak>
                <CSWeak weigth="1.035348" v0="650802880" v1="197469816" v2="1683914460" v3="1143502068" v4="3233816670" v5="3690158120" v6="1173747700" v7="1127323494" v8="1850509162" v9="1398881213" v10="164445308" v11="208644981" v12="869243767" v13="1501548211" v14="1031697858" v15="56177682">
                    <CSFeature sxBase="9" syBase="13" wBase="1" hBase="1" />
                </CSWeak>
                <CSWeak weigth="1.033461" v0="2049598154" v1="3655706709" v2="1408644843" v3="2399333811" v4="3659518632" v5="3049650783" v6="2614740415" v7="490885402" v8="3463991679" v9="3749421025" v10="2006047765" v11="2007212152" v12="3133762070" v13="2140306855" v14="3194349363" v15="1729789429">
                    <CSFeature sxBase="1" syBase="1" wBase="1" hBase="1" />
                </CSWeak>
                <CSWeak weigth="1.044828" v0="2255112800" v1="1960432841" v2="2467571243" v3="2531998528" v4="2913000826" v5="1427577947" v6="4154020092" v7="1448554291" v8="2413502017" v9="384654293" v10="192394221" v11="393647541" v12="2067663480" v13="4224711931" v14="2145101110" v15="1433877840">
                    <CSFeature sxBase="1" syBase="18" wBase="1" hBase="1" />
                </CSWeak>
                <CSWeak weigth="1.060524" v0="2143818318" v1="3321572352" v2="2445033431" v3="4117915203" v4="1500181878" v5="1442860868" v6="3986149102" v7="1528720893" v8="2442010920" v9="1479106415" v10="1001248743" v11="4107746371" v12="887974970" v13="1043667532" v14="2639526751" v15="1062803960">
                    <CSFeature sxBase="0" syBase="2" wBase="1" hBase="1" />
                </CSWeak>
                <CSWeak weigth="1.059876" v0="3188382058" v1="2157444730" v2="4088119026" v3="4067816410" v4="3745643426" v5="914404024" v6="3342810101" v7="2015763267" v8="1824824126" v9="3733818545" v10="1956293447" v11="2549948649" v12="1858497974" v13="3606724548" v14="1215101283" v15="36257343">
                    <CSFeature sxBase="7" syBase="0" wBase="2" hBase="1" />
                </CSWeak>
                <CSWeak weigth="1.101524" v0="61920448" v1="1498380084" v2="3741712154" v3="4072434645" v4="1978377237" v5="130514790" v6="3992956711" v7="3714908082" v8="1829434207" v9="4193293765" v10="130916340" v11="295473631" v12="2612187106" v13="2497046385" v14="1064299957" v15="1256858087">
                    <CSFeature sxBase="18" syBase="16" wBase="1" hBase="1" />
                </CSWeak>
                <CSWeak weigth="1.123170" v0="3642887856" v1="2187198825" v2="3939293926" v3="3215105596" v4="8329232" v5="4198985674" v6="2821693377" v7="1998483339" v8="967621238" v9="3573747564" v10="3103459481" v11="84227803" v12="1111311835" v13="1599095786" v14="1131559911" v15="492176868">
                    <CSFeature sxBase="14" syBase="15" wBase="1" hBase="1" />
                </CSWeak>
                <CSWeak weigth="1.119008" v0="2370060880" v1="665933809" v2="396400404" v3="4084022806" v4="104888776" v5="1312413156" v6="3259885167" v7="140802645" v8="3388296117" v9="2096431088" v10="2529676408" v11="262168558" v12="4067763669" v13="3069702138" v14="506285098" v15="491462301">
                    <CSFeature sxBase="4" syBase="16" wBase="1" hBase="1" />
                </CSWeak>
                <CSWeak weigth="1.127658" v0="1786904592" v1="2644442360" v2="4191049392" v3="862690252" v4="1016985634" v5="2949595692" v6="771160303" v7="1165712127" v8="4293776486" v9="2595741412" v10="908531232" v11="1187468388" v12="1958639079" v13="1393712428" v14="1082030585" v15="1126171234">
                    <CSFeature sxBase="9" syBase="8" wBase="2" hBase="1" />
                </CSWeak>
                <CSWeak weigth="1.110714" v0="645850864" v1="2607570756" v2="3757718919" v3="2947877457" v4="4157282206" v5="1860946800" v6="2133310807" v7="1601224205" v8="750462975" v9="3185014679" v10="3877093190" v11="1117014987" v12="3314470865" v13="2944791949" v14="2980304637" v15="1266301337">
                    <CSFeature sxBase="16" syBase="18" wBase="1" hBase="1" />
                </CSWeak>
                <CSWeak weigth="1.105061" v0="182346312" v1="3421284058" v2="2135355391" v3="1824085299" v4="4209773646" v5="1329735836" v6="4251393918" v7="1578980385" v8="244230314" v9="3064884742" v10="759914215" v11="1258864317" v12="3327858942" v13="2069575884" v14="357443229" v15="303770124">
                    <CSFeature sxBase="6" syBase="3" wBase="3" hBase="1" />
                </CSWeak>
                <CSWeak weigth="1.136035" v0="24261848" v1="241618168" v2="606551254" v3="608914578" v4="3031715520" v5="1019735143" v6="3953735120" v7="2420178316" v8="2097285244" v9="1811326923" v10="2682971591" v11="1663612013" v12="2867122406" v13="1741409901" v14="468667854" v15="1464796555">
                    <CSFeature sxBase="0" syBase="15" wBase="1" hBase="1" />
                </CSWeak>
                <CSWeak weigth="1.191853" v0="1121235008" v1="3875161706" v2="3841974142" v3="386822420" v4="2510261808" v5="2398469099" v6="2669672110" v7="4260048916" v8="4185343000" v9="4174548254" v10="1432559282" v11="3614281138" v12="864737397" v13="938337520" v14="1267955615" v15="793213305">
                    <CSFeature sxBase="2" syBase="18" wBase="1" hBase="1" />
                </CSWeak>
                <CSWeak weigth="1.135412" v0="2968286442" v1="2078848244" v2="3471063412" v3="79557206" v4="3396600288" v5="3556752006" v6="1685492785" v7="102512758" v8="1741442878" v9="2455043764" v10="1727515900" v11="142526009" v12="3321946271" v13="3669212092" v14="746325137" v15="1392919636">
                    <CSFeature sxBase="8" syBase="15" wBase="1" hBase="1" />
                </CSWeak>
            </CSClassificator>
            <CSClassificator threshold="6.420120">
                <CSWeak weigth="0.862347" v0="0" v1="0" v2="0" v3="2097184" v4="41634" v5="43650" v6="2216" v7="43690" v8="0" v9="0" v10="536870944" v11="32" v12="2132488" v13="8192" v14="539099304" v15="128">
                    <CSFeature sxBase="0" syBase="0" wBase="7" hBase="7" />
                </CSWeak>
                <CSWeak weigth="0.897470" v0="33554440" v1="33554432" v2="50866696" v3="2560" v4="33555072" v5="0" v6="50342408" v7="16785408" v8="134218240" v9="134219407" v10="167939624" v11="33557002" v12="167837728" v13="16973828" v14="201225" v15="8192">
                    <CSFeature sxBase="0" syBase="18" wBase="7" hBase="1" />
                </CSWeak>
                <CSWeak weigth="0.826164" v0="671252496" v1="40960" v2="2" v3="67109424" v4="19110" v5="128" v6="16777328" v7="117" v8="64" v9="8388608" v10="67108864" v11="67108864" v12="43050" v13="128" v14="285278259" v15="83951616">
                    <CSFeature sxBase="3" syBase="7" wBase="6" hBase="2" />
                </CSWeak>
                <CSWeak weigth="0.818270" v0="2415935616" v1="2995175552" v2="2228234" v3="633046415" v4="3608432744" v5="3221309636" v6="134743246" v7="1175210447" v8="4080038136" v9="4206510088" v10="1228017812" v11="330973192" v12="1880128210" v13="4214014056" v14="138433648" v15="168430218">
                    <CSFeature sxBase="2" syBase="8" wBase="2" hBase="1" />
                </CSWeak>
                <CSWeak weigth="0.761970" v0="83888128" v1="272369152" v2="12" v3="4096" v4="856097576" v5="889405457" v6="1163153680" v7="30765412" v8="3261936728" v9="1473003588" v10="286295124" v11="911544370" v12="459223846" v13="254628717" v14="1394415447" v15="292893556">
                    <CSFeature sxBase="0" syBase="18" wBase="3" hBase="1" />
                </CSWeak>
                <CSWeak weigth="0.774598" v0="1140873730" v1="1578620538" v2="3005614096" v3="884158522" v4="2754796170" v5="2217354794" v6="283775135" v7="1093482684" v8="3070261968" v9="967188234" v10="2215268424" v11="16672" v12="446854087" v13="537139336" v14="890717683" v15="1090716482">
                    <CSFeature sxBase="10" syBase="9" wBase="2" hBase="1" />
                </CSWeak>
                <CSWeak weigth="0.771398" v0="3120584768" v1="1877703296" v2="146312236" v3="2125398191" v4="2584828512" v5="235561028" v6="1083133486" v7="191696239" v8="930770946" v9="1006511113" v10="923818179" v11="121506600" v12="846852210" v13="1476809220" v14="537678949" v15="118111780">
                    <CSFeature sxBase="4" syBase="7" wBase="2" hBase="1" />
                </CSWeak>
                <CSWeak weigth="0.774451" v0="239888984" v1="4219999008" v2="2074046223" v3="4122979008" v4="1263011852" v5="16910891" v6="273243911" v7="1292583783" v8="1182827080" v9="101842963" v10="35553245" v11="185501703" v12="13151724" v13="2621832" v14="38014814" v15="235408410">
                    <CSFeature sxBase="0" syBase="0" wBase="6" hBase="2" />
                </CSWeak>
                <CSWeak weigth="0.740139" v0="541589824" v1="2800003488" v2="1150002304" v3="2873476100" v4="1231066658" v5="3520130776" v6="3382516016" v7="305579116" v8="2046009633" v9="4070698668" v10="3976581145" v11="1763094468" v12="2702639186" v13="3114401767" v14="505229060" v15="1442987781">
                    <CSFeature sxBase="7" syBase="18" wBase="1" hBase="1" />
                </CSWeak>
                <CSWeak weigth="0.754725" v0="2281736192" v1="2132000" v2="2281701376" v3="134219808" v4="2056" v5="2176" v6="32" v7="184" v8="134219808" v9="35360" v10="544" v11="0" v12="10752" v13="0" v14="10274" v15="32">
                    <CSFeature sxBase="5" syBase="6" wBase="5" hBase="5" />
                </CSWeak>
                <CSWeak weigth="0.800679" v0="1716344" v1="252632138" v2="806490136" v3="235881087" v4="572584106" v5="604536056" v6="10486948" v7="287966719" v8="4235227154" v9="3194364928" v10="345647282" v11="70201440" v12="582119597" v13="1631584256" v14="302649560" v15="117440526">
                    <CSFeature sxBase="5" syBase="10" wBase="3" hBase="1" />
                </CSWeak>
                <CSWeak weigth="0.748568" v0="2815965704" v1="2177755373" v2="934250920" v3="2211481632" v4="1163150952" v5="4207104502" v6="586392721" v7="2294516258" v8="298821972" v9="2829122469" v10="2294938288" v11="513451530" v12="1376696796" v13="564297646" v14="252390146" v15="161567">
                    <CSFeature sxBase="9" syBase="18" wBase="1" hBase="1" />
                </CSWeak>
                <CSWeak weigth="0.759093" v0="1684957282" v1="1899126882" v2="140118464" v3="926650474" v4="1100007464" v5="1616252954" v6="1936983114" v7="67589226" v8="1137985812" v9="1966426176" v10="1890213117" v11="359977996" v12="1935046085" v13="293624392" v14="68046062" v15="285610018">
                    <CSFeature sxBase="12" syBase="7" wBase="2" hBase="1" />
                </CSWeak>
                <CSWeak weigth="0.781476" v0="1436055616" v1="3076845696" v2="1496449198" v3="3202285711" v4="1095131360" v5="3217051842" v6="1351" v7="43385935" v8="4172872384" v9="4237709315" v10="892862540" v11="37671466" v12="4176891984" v13="318947410" v14="455082245" v15="58851590">
                    <CSFeature sxBase="1" syBase="9" wBase="2" hBase="1" />
                </CSWeak>
                <CSWeak weigth="0.755878" v0="2123657820" v1="254443096" v2="1243914240" v3="918491598" v4="1686666846" v5="2281733184" v6="2617560397" v7="123108175" v8="3060855536" v9="1069498381" v10="1413372018" v11="183386635" v12="1917515921" v13="923140364" v14="253694194" v15="99354154">
                    <CSFeature sxBase="6" syBase="7" wBase="2" hBase="1" />
                </CSWeak>
                <CSWeak weigth="0.745898" v0="32768" v1="281575552" v2="270663680" v3="13648008" v4="165920" v5="4329672" v6="2097186" v7="9439444" v8="2129962" v9="177115288" v10="131072" v11="1179874" v12="131104" v13="306249801" v14="131390" v15="20596">
                    <CSFeature sxBase="7" syBase="8" wBase="2" hBase="4" />
                </CSWeak>
                <CSWeak weigth="0.783748" v0="713166460" v1="2835286568" v2="384754080" v3="3740950075" v4="820641832" v5="128226940" v6="1881412773" v7="1192218863" v8="2799710930" v9="993666853" v10="100720823" v11="3478676994" v12="2025995280" v13="321215490" v14="1342708464" v15="387320002">
                    <CSFeature sxBase="7" syBase="6" wBase="2" hBase="1" />
                </CSWeak>
                <CSWeak weigth="0.795578" v0="2008160834" v1="2121006754" v2="3918531592" v3="3443393194" v4="841119344" v5="1544210154" v6="20686" v7="285605993" v8="4059488753" v9="2132346114" v10="369047480" v11="84148640" v12="12255190" v13="1443040256" v14="391332347" v15="520619018">
                    <CSFeature sxBase="8" syBase="9" wBase="3" hBase="1" />
                </CSWeak>
                <CSWeak weigth="0.786367" v0="2141895224" v1="69884462" v2="2708666482" v3="2161135732" v4="2491443754" v5="346612240" v6="337776752" v7="791420" v8="2595401824" v9="541823687" v10="606470336" v11="17056312" v12="17170960" v13="9592849" v14="120524804" v15="85983497">
                    <CSFeature sxBase="9" syBase="11" wBase="2" hBase="2" />
                </CSWeak>
                <CSWeak weigth="0.763145" v0="982523952" v1="3994182144" v2="35458993" v3="687741884" v4="268465216" v5="1287482622" v6="68836812" v7="197075439" v8="4257069280" v9="779828264" v10="1190691056" v11="503513705" v12="1283390704" v13="184811520" v14="407114429" v15="1191838862">
                    <CSFeature sxBase="5" syBase="8" wBase="3" hBase="1" />
                </CSWeak>
            </CSClassificator>
            <CSClassificator threshold="8.048773">
                <CSWeak weigth="0.769973" v0="0" v1="4" v2="33555456" v3="67108928" v4="0" v5="0" v6="524352" v7="134218464" v8="8" v9="2048" v10="167776256" v11="50331648" v12="184553480" v13="50331904" v14="458905168" v15="50332160">
                    <CSFeature sxBase="0" syBase="3" wBase="4" hBase="3" />
                </CSWeak>
                <CSWeak weigth="0.757074" v0="512" v1="8704" v2="33948426" v3="6912" v4="25174016" v5="2097184" v6="553651712" v7="512" v8="704749090" v9="422522378" v10="168506883" v11="1342210594" v12="171903506" v13="588120736" v14="139794" v15="83898368">
                    <CSFeature sxBase="0" syBase="18" wBase="6" hBase="1" />
                </CSWeak>
                <CSWeak weigth="0.708568" v0="41984000" v1="167938048" v2="40960" v3="41994264" v4="545294848" v5="23069258" v6="33024" v7="33554944" v8="418833042" v9="2562436300" v10="738205696" v11="218105902" v12="37748800" v13="263729656" v14="50332674" v15="303235840">
                    <CSFeature sxBase="7" syBase="15" wBase="2" hBase="2" />
                </CSWeak>
                <CSWeak weigth="0.714395" v0="1478645800" v1="1949821480" v2="2046296290" v3="4143898922" v4="1176693962" v5="6907454" v6="2151713929" v7="2165833898" v8="2003825009" v9="1419067528" v10="1915330610" v11="220598336" v12="352509765" v13="285295936" v14="1150821574" v15="268571707">
                    <CSFeature sxBase="11" syBase="9" wBase="3" hBase="1" />
                </CSWeak>
                <CSWeak weigth="0.696415" v0="812802160" v1="606403688" v2="271781908" v3="138023087" v4="33587296" v5="136328268" v6="303170861" v7="402984431" v8="4243599408" v9="3061459616" v10="41156848" v11="243401002" v12="292565025" v13="4328524" v14="186778228" v15="185075714">
                    <CSFeature sxBase="1" syBase="9" wBase="4" hBase="1" />
                </CSWeak>
                <CSWeak weigth="0.708093" v0="1878949706" v1="822029960" v2="1742602207" v3="271775985" v4="738749960" v5="323108578" v6="3966599143" v7="1421536879" v8="359195882" v9="218402050" v10="1411382255" v11="19887599" v12="105865210" v13="1629681120" v14="134766684" v15="172363340">
                    <CSFeature sxBase="7" syBase="0" wBase="3" hBase="2" />
                </CSWeak>
                <CSWeak weigth="0.693009" v0="1759928872" v1="1272870638" v2="858653674" v3="2532461496" v4="503966789" v5="84198492" v6="2620399733" v7="1870158060" v8="1725974144" v9="1308565902" v10="723551803" v11="1099188436" v12="1142474237" v13="1279321161" v14="1159333117" v15="1427838272">
                    <CSFeature sxBase="6" syBase="6" wBase="5" hBase="1" />
                </CSWeak>
                <CSWeak weigth="0.710436" v0="1457128008" v1="1693772973" v2="2956165567" v3="4024838690" v4="131089920" v5="4143481568" v6="96709777" v7="994384739" v8="316129232" v9="2225185190" v10="2236279468" v11="2685743414" v12="4260703926" v13="1302385581" v14="1971066282" v15="156579631">
                    <CSFeature sxBase="8" syBase="18" wBase="1" hBase="1" />
                </CSWeak>
                <CSWeak weigth="0.706239" v0="0" v1="2592" v2="0" v3="2562" v4="43040" v5="10760" v6="2048" v7="33314" v8="0" v9="32" v10="35651618" v11="0" v12="165896" v13="0" v14="589441066" v15="131082">
                    <CSFeature sxBase="3" syBase="0" wBase="6" hBase="7" />
                </CSWeak>
                <CSWeak weigth="0.765377" v0="1563086912" v1="2095805480" v2="1559372888" v3="211667099" v4="598650070" v5="1311757998" v6="2082112652" v7="475988303" v8="1937335410" v9="3196453125" v10="1207688669" v11="38490305" v12="850576217" v13="604528644" v14="283134650" v15="1512850506">
                    <CSFeature sxBase="7" syBase="7" wBase="3" hBase="1" />
                </CSWeak>
                <CSWeak weigth="0.736457" v0="1484279904" v1="2091809896" v2="1319504486" v3="203166970" v4="2621444232" v5="1145949774" v6="390599437" v7="205529071" v8="4042403888" v9="2116287565" v10="23105188" v11="267259304" v12="50341898" v13="843843726" v14="491329591" v15="139008672">
                    <CSFeature sxBase="2" syBase="7" wBase="5" hBase="1" />
                </CSWeak>
                <CSWeak weigth="0.754478" v0="650117250" v1="3789939877" v2="894218506" v3="2191535316" v4="208718149" v5="1626749652" v6="9571527" v7="178329925" v8="9676020" v9="3183012768" v10="3432440824" v11="1288153251" v12="809341264" v13="2587156390" v14="525935668" v15="107484484">
                    <CSFeature sxBase="7" syBase="17" wBase="1" hBase="1" />
                </CSWeak>
                <CSWeak weigth="0.738652" v0="2113415200" v1="156696597" v2="3507998689" v3="2034467195" v4="2035621196" v5="1931828486" v6="2000655711" v7="1459900001" v8="3875540854" v9="2400200721" v10="1333688058" v11="1078133380" v12="2450930452" v13="1862735259" v14="1057197005" v15="289611357">
                    <CSFeature sxBase="18" syBase="15" wBase="1" hBase="2" />
                </CSWeak>
                <CSWeak weigth="0.723958" v0="346434144" v1="2017360104" v2="2024673358" v3="405317368" v4="677706893" v5="584815" v6="486940717" v7="1074419111" v8="4034582738" v9="4131153216" v10="2296520945" v11="134688360" v12="21027925" v13="219309384" v14="424806401" v15="1145636804">
                    <CSFeature sxBase="4" syBase="8" wBase="5" hBase="1" />
                </CSWeak>
                <CSWeak weigth="0.730848" v0="1342720032" v1="1847294024" v2="1350303750" v3="219026063" v4="269545712" v5="874274024" v6="2114959" v7="488013263" v8="3069327472" v9="2843607340" v10="318111793" v11="78579986" v12="640702129" v13="541590536" v14="319429206" v15="50856456">
                    <CSFeature sxBase="4" syBase="9" wBase="3" hBase="1" />
                </CSWeak>
                <CSWeak weigth="0.749564" v0="1508377740" v1="1333321356" v2="3349911729" v3="3435586216" v4="2220903488" v5="4194172338" v6="2765154062" v7="1074102848" v8="3462318310" v9="3752656672" v10="3767533505" v11="2249654084" v12="402658372" v13="1353758587" v14="3604484" v15="84148489">
                    <CSFeature sxBase="9" syBase="16" wBase="1" hBase="1" />
                </CSWeak>
                <CSWeak weigth="0.741908" v0="3091222026" v1="1546394666" v2="852630136" v3="158281978" v4="1688906258" v5="3301978680" v6="279843867" v7="325275832" v8="1987471962" v9="505479738" v10="846543384" v11="554369146" v12="1622337673" v13="200066" v14="1093890288" v15="69892">
                    <CSFeature sxBase="9" syBase="10" wBase="2" hBase="1" />
                </CSWeak>
                <CSWeak weigth="0.754324" v0="4293457928" v1="2762592490" v2="3074636994" v3="4287687825" v4="3496051916" v5="3482904566" v6="2419550227" v7="1599410741" v8="3915612035" v9="1999684869" v10="1477907613" v11="171810839" v12="1499924507" v13="204167246" v14="274823071" v15="236940925">
                    <CSFeature sxBase="0" syBase="0" wBase="2" hBase="1" />
                </CSWeak>
                <CSWeak weigth="0.739199" v0="3002493044" v1="1743929150" v2="713149490" v3="852164322" v4="2517295080" v5="3418655224" v6="3864483054" v7="1115174539" v8="3276188521" v9="4217548500" v10="877110291" v11="2864339979" v12="594586228" v13="713950028" v14="9078906" v15="453649420">
                    <CSFeature sxBase="7" syBase="4" wBase="1" hBase="1" />
                </CSWeak>
                <CSWeak weigth="0.746018" v0="3799040000" v1="2171921554" v2="1087832388" v3="1432214032" v4="2450166496" v5="3637363964" v6="1372913922" v7="1183680066" v8="3812729092" v9="4175560680" v10="2880619473" v11="1573890385" v12="743779857" v13="3752654257" v14="1061104486" v15="1595350911">
                    <CSFeature sxBase="5" syBase="18" wBase="1" hBase="1" />
                </CSWeak>
                <CSWeak weigth="0.735695" v0="1363820550" v1="2607684333" v2="1657222901" v3="1813820134" v4="1149976768" v5="3598125656" v6="1456930045" v7="200693198" v8="528380670" v9="3009723051" v10="1100210654" v11="72657604" v12="1931944145" v13="1534975730" v14="1036018888" v15="67588098">
                    <CSFeature sxBase="9" syBase="11" wBase="1" hBase="1" />
                </CSWeak>
                <CSWeak weigth="0.734540" v0="4162896424" v1="539707466" v2="481427466" v3="870977626" v4="537196618" v5="17068120" v6="2366804006" v7="1476790310" v8="2113359989" v9="4219970" v10="883106962" v11="339869762" v12="1343247700" v13="1364612481" v14="1410483331" v15="272831515">
                    <CSFeature sxBase="12" syBase="8" wBase="3" hBase="1" />
                </CSWeak>
                <CSWeak weigth="0.747126" v0="3439904800" v1="1702650216" v2="615269928" v3="1857964719" v4="2215649000" v5="855929420" v6="205533246" v7="504845519" v8="4218598026" v9="590527456" v10="570431685" v11="322390543" v12="540850296" v13="453717539" v14="168979481" v15="193858084">
                    <CSFeature sxBase="4" syBase="6" wBase="2" hBase="1" />
                </CSWeak>
                <CSWeak weigth="0.750625" v0="2065745992" v1="1118507082" v2="3775041546" v3="3061531242" v4="2416754698" v5="2585956584" v6="1109567658" v7="1245227432" v8="4114731632" v9="3578921024" v10="354551265" v11="1343246760" v12="1431590101" v13="1225875468" v14="269287663" v15="1512499">
                    <CSFeature sxBase="15" syBase="9" wBase="2" hBase="1" />
                </CSWeak>
                <CSWeak weigth="0.774808" v0="3105378312" v1="3460934152" v2="627317226" v3="1182686207" v4="1755820758" v5="1245268134" v6="283555279" v7="151615935" v8="4092473380" v9="1940703813" v10="111967272" v11="1309137694" v12="1931993820" v13="740892" v14="348271344" v15="102172584">
                    <CSFeature sxBase="8" syBase="8" wBase="2" hBase="1" />
                </CSWeak>
            </CSClassificator>
            <CSClassificator threshold="6.711400">
                <CSWeak weigth="0.856993" v0="316286496" v1="3857772189" v2="4059534751" v3="252357666" v4="1875928064" v5="3598244336" v6="614240186" v7="860560233" v8="2532824496" v9="2913447850" v10="3436297103" v11="2685860128" v12="3170348466" v13="1554185642" v14="1985879458" v15="425014638">
                    <CSFeature sxBase="8" syBase="18" wBase="1" hBase="1" />
                </CSWeak>
                <CSWeak weigth="0.897144" v0="1203806240" v1="2945276009" v2="341129225" v3="3233757783" v4="2942852442" v5="2535180863" v6="997966201" v7="1330460558" v8="3879687248" v9="2237554629" v10="1533901695" v11="1346866119" v12="1935634262" v13="3209148304" v14="1435500383" v15="1361264539">
                    <CSFeature sxBase="1" syBase="18" wBase="1" hBase="1" />
                </CSWeak>
                <CSWeak weigth="0.943634" v0="1817728592" v1="2129968712" v2="3588906618" v3="18312719" v4="2109453396" v5="768536734" v6="1220070699" v7="1262436351" v8="4277186618" v9="4289722153" v10="1609963960" v11="320016295" v12="173563527" v13="187308769" v14="856164779" v15="457704810">
                    <CSFeature sxBase="6" syBase="7" wBase="3" hBase="1" />
                </CSWeak>
                <CSWeak weigth="0.950486" v0="349330002" v1="265245208" v2="1812753032" v3="1342100059" v4="238713488" v5="2346764522" v6="2008641773" v7="340620030" v8="4277203530" v9="4166209439" v10="1952282722" v11="119478869" v12="2078210670" v13="492192593" v14="355954920" v15="1077282314">
                    <CSFeature sxBase="7" syBase="11" wBase="2" hBase="1" />
                </CSWeak>
                <CSWeak weigth="0.947274" v0="1006384864" v1="685293218" v2="2616510778" v3="1319063544" v4="3211045888" v5="3204018940" v6="4059940683" v7="3718647004" v8="2925193902" v9="749600422" v10="2742614226" v11="577238539" v12="1341137434" v13="2650925732" v14="1242183692" v15="239272710">
                    <CSFeature sxBase="10" syBase="17" wBase="1" hBase="1" />
                </CSWeak>
                <CSWeak weigth="0.993671" v0="3611694354" v1="3594389244" v2="954982270" v3="2380001279" v4="3654273260" v5="3746329308" v6="4019576615" v7="1342150214" v8="1761465522" v9="3207031457" v10="703328043" v11="4000283925" v12="2057039869" v13="1973698492" v14="1646603111" v15="142886574">
                    <CSFeature sxBase="13" syBase="1" wBase="1" hBase="1" />
                </CSWeak>
                <CSWeak weigth="0.971883" v0="1573827180" v1="4211336606" v2="782656719" v3="3735243854" v4="4294109549" v5="1248310291" v6="3196021469" v7="1071576861" v8="1456959660" v9="2066173677" v10="1467981823" v11="1556273687" v12="1880273822" v13="1005883245" v14="1910488933" v15="1916564731">
                    <CSFeature sxBase="16" syBase="0" wBase="1" hBase="1" />
                </CSWeak>
                <CSWeak weigth="0.964866" v0="2147228510" v1="3849124604" v2="4126112915" v3="3115317992" v4="3941238570" v5="2145348880" v6="3630086618" v7="4015431367" v8="4009407211" v9="1866460889" v10="998240252" v11="523388924" v12="1809768179" v13="1572727976" v14="753976884" v15="689443796">
                    <CSFeature sxBase="11" syBase="3" wBase="1" hBase="1" />
                </CSWeak>
                <CSWeak weigth="0.991572" v0="1532689566" v1="3455608653" v2="3411638167" v3="1790547309" v4="3141466800" v5="4149962715" v6="3016883591" v7="2923001509" v8="3755206318" v9="3720307171" v10="528199159" v11="366166245" v12="4275616119" v13="428762620" v14="2051612606" v15="1568089482">
                    <CSFeature sxBase="16" syBase="17" wBase="1" hBase="1" />
                </CSWeak>
                <CSWeak weigth="0.986295" v0="3977438250" v1="1256634602" v2="4193447407" v3="2027372458" v4="3181952815" v5="3645895125" v6="3560959726" v7="4243414989" v8="469250966" v9="3085000230" v10="2103122743" v11="3364220907" v12="2577399022" v13="3732912888" v14="498297245" v15="1194539372">
                    <CSFeature sxBase="5" syBase="1" wBase="1" hBase="1" />
                </CSWeak>
                <CSWeak weigth="1.022054" v0="3078546220" v1="2073950379" v2="4261025787" v3="3022728650" v4="759459720" v5="2566112783" v6="2699283311" v7="370810011" v8="2072476522" v9="654231025" v10="3698529055" v11="3606720758" v12="2666578765" v13="4217312614" v14="1014857599" v15="840374247">
                    <CSFeature sxBase="6" syBase="0" wBase="1" hBase="1" />
                </CSWeak>
                <CSWeak weigth="1.008299" v0="930143880" v1="3111192492" v2="1132099030" v3="267621629" v4="3060223645" v5="1317009338" v6="3245865964" v7="2675959229" v8="1070758231" v9="4106183987" v10="133796669" v11="1088389567" v12="2651432421" v13="2637952589" v14="998235755" v15="1324300214">
                    <CSFeature sxBase="18" syBase="16" wBase="1" hBase="1" />
                </CSWeak>
                <CSWeak weigth="1.000112" v0="925655666" v1="670467564" v2="4013752156" v3="1039723952" v4="1588537608" v5="1944783098" v6="3386356733" v7="985588161" v8="2379885750" v9="4005229499" v10="1558177279" v11="37444586" v12="2147482489" v13="31603692" v14="1381056254" v15="273446142">
                    <CSFeature sxBase="9" syBase="2" wBase="2" hBase="1" />
                </CSWeak>
                <CSWeak weigth="1.030587" v0="2620024938" v1="1775218358" v2="1441705883" v3="1605355471" v4="3546474482" v5="2078747385" v6="3753798363" v7="3648810987" v8="3254729963" v9="2851716173" v10="2952574766" v11="402860536" v12="2072456121" v13="3727101831" v14="375907951" v15="390354663">
                    <CSFeature sxBase="11" syBase="0" wBase="1" hBase="1" />
                </CSWeak>
                <CSWeak weigth="1.032010" v0="826829024" v1="311606942" v2="4260364051" v3="275765113" v4="3123379651" v5="4008701910" v6="3609634743" v7="1090993942" v8="536736668" v9="1762487243" v10="4218402103" v11="2640259805" v12="1670838949" v13="3689257812" v14="2087579551" v15="54730621">
                    <CSFeature sxBase="0" syBase="18" wBase="1" hBase="1" />
                </CSWeak>
                <CSWeak weigth="1.075981" v0="1619945596" v1="4026366620" v2="2524937450" v3="1048569471" v4="1950408324" v5="1585064106" v6="3158293710" v7="1262751329" v8="3193092835" v9="2579815101" v10="139590872" v11="1040137327" v12="749432439" v13="1830611638" v14="1900837591" v15="996817930">
                    <CSFeature sxBase="5" syBase="5" wBase="1" hBase="1" />
                </CSWeak>
            </CSClassificator>
            <CSClassificator threshold="6.943571">
                <CSWeak weigth="1.000561" v0="0" v1="0" v2="0" v3="32" v4="0" v5="0" v6="0" v7="4194528" v8="0" v9="0" v10="4096" v11="16777376" v12="268435456" v13="0" v14="326324338" v15="16843004">
                    <CSFeature sxBase="4" syBase="1" wBase="3" hBase="6" />
                </CSWeak>
                <CSWeak weigth="0.777619" v0="0" v1="4194304" v2="8388736" v3="192" v4="0" v5="64" v6="192" v7="96" v8="0" v9="0" v10="50331648" v11="0" v12="285216832" v13="0" v14="285216848" v15="0">
                    <CSFeature sxBase="0" syBase="4" wBase="4" hBase="3" />
                </CSWeak>
                <CSWeak weigth="0.763361" v0="2418018304" v1="268567050" v2="655528" v3="2863268394" v4="2097290" v5="2760392904" v6="2147483816" v7="1653215274" v8="1970402628" v9="1898578176" v10="1144213704" v11="823263266" v12="285236581" v13="285233417" v14="269485284" v15="1079136288">
                    <CSFeature sxBase="15" syBase="8" wBase="2" hBase="1" />
                </CSWeak>
                <CSWeak weigth="0.796449" v0="2281734144" v1="34848" v2="2281701376" v3="32" v4="0" v5="32" v6="0" v7="34" v8="2048" v9="128" v10="0" v11="0" v12="2056" v13="32" v14="131114" v15="131120">
                    <CSFeature sxBase="7" syBase="6" wBase="4" hBase="4" />
                </CSWeak>
                <CSWeak weigth="0.728651" v0="0" v1="2199846924" v2="168558640" v3="1140982017" v4="135266432" v5="17133640" v6="23020804" v7="4591911" v8="285622336" v9="118424872" v10="4785408" v11="190775646" v12="219283968" v13="1604784424" v14="1632864005" v15="318898513">
                    <CSFeature sxBase="0" syBase="12" wBase="2" hBase="3" />
                </CSWeak>
                <CSWeak weigth="0.721102" v0="3101698602" v1="270674568" v2="2902071466" v3="581574826" v4="3498113802" v5="137312776" v6="536903914" v7="3623880714" v8="4201895269" v9="16384" v10="817057840" v11="2228258" v12="1900043733" v13="5132" v14="196" v15="269418543">
                    <CSFeature sxBase="12" syBase="10" wBase="3" hBase="1" />
                </CSWeak>
                <CSWeak weigth="0.759938" v0="2487621642" v1="863969802" v2="2988613738" v3="725295418" v4="1420904458" v5="27084926" v6="539234330" v7="1095636266" v8="4183126132" v9="426971465" v10="805569361" v11="1416736835" v12="1389000005" v13="1431360084" v14="1611285742" v15="69606414">
                    <CSFeature sxBase="14" syBase="6" wBase="2" hBase="1" />
                </CSWeak>
                <CSWeak weigth="0.746766" v0="1881540650" v1="1651534368" v2="787619912" v3="11143480" v4="1357440072" v5="274107108" v6="549983846" v7="1095635614" v8="4067184963" v9="810842432" v10="1944466642" v11="72434774" v12="1091657045" v13="1426479173" v14="1899186399" v15="1428377939">
                    <CSFeature sxBase="11" syBase="7" wBase="3" hBase="1" />
                </CSWeak>
                <CSWeak weigth="0.727884" v0="1935683680" v1="790315530" v2="2707312678" v3="737105934" v4="320884808" v5="3289305280" v6="810589198" v7="268777503" v8="859338848" v9="3744596992" v10="19404832" v11="20643875" v12="886239984" v13="1087434816" v14="352326001" v15="50856192">
                    <CSFeature sxBase="5" syBase="10" wBase="2" hBase="1" />
                </CSWeak>
                <CSWeak weigth="0.725629" v0="4227072" v1="1389961344" v2="4196416" v3="5242918" v4="49344" v5="15859920" v6="7356416" v7="11550810" v8="172064" v9="1206620296" v10="32" v11="5275664" v12="2082" v13="1082851444" v14="98" v15="1048658">
                    <CSFeature sxBase="6" syBase="8" wBase="2" hBase="4" />
                </CSWeak>
                <CSWeak weigth="0.725378" v0="1947891760" v1="1969159722" v2="1089208334" v3="2932736135" v4="1247998706" v5="40304316" v6="49433743" v7="1160543407" v8="4122226938" v9="3998639168" v10="1449537906" v11="122294912" v12="1880290644" v13="864555076" v14="1495945369" v15="1124730378">
                    <CSFeature sxBase="6" syBase="9" wBase="3" hBase="1" />
                </CSWeak>
                <CSWeak weigth="0.736361" v0="635437586" v1="707748414" v2="1727294548" v3="2370481359" v4="41844464" v5="333636264" v6="81724741" v7="107222764" v8="1934982640" v9="925957935" v10="3698077214" v11="38609029" v12="603160179" v13="372921370" v14="89547858" v15="1178882496">
                    <CSFeature sxBase="8" syBase="12" wBase="1" hBase="1" />
                </CSWeak>
                <CSWeak weigth="0.718936" v0="874140264" v1="2137147720" v2="602827534" v3="2950673583" v4="1616307816" v5="2818758744" v6="444917039" v7="70175375" v8="3014718160" v9="1979025156" v10="506793624" v11="326044163" v12="2081970773" v13="504124489" v14="1376195507" v15="51249315">
                    <CSFeature sxBase="5" syBase="7" wBase="2" hBase="1" />
                </CSWeak>
                <CSWeak weigth="0.724177" v0="2468635144" v1="2854423106" v2="581074984" v3="2948286634" v4="2483601546" v5="213949002" v6="2149728266" v7="2194276394" v8="4084291024" v9="352522248" v10="1394741751" v11="1360023656" v12="1415664989" v13="1226079304" v14="269222108" v15="269817894">
                    <CSFeature sxBase="15" syBase="9" wBase="2" hBase="1" />
                </CSWeak>
                <CSWeak weigth="0.721462" v0="4023673952" v1="480409254" v2="1388809274" v3="4022396970" v4="3717882456" v5="4294891002" v6="3235029256" v7="168706060" v8="3278432422" v9="2432872365" v10="1458503114" v11="2382351862" v12="917610616" v13="3660232098" v14="1897012289" v15="755171848">
                    <CSFeature sxBase="9" syBase="17" wBase="1" hBase="1" />
                </CSWeak>
                <CSWeak weigth="0.742130" v0="811616866" v1="820656650" v2="184229946" v3="593635698" v4="83860136" v5="1158498360" v6="1172471936" v7="340011098" v8="4154873847" v9="1347620948" v10="904278370" v11="1146375280" v12="1433949525" v13="312291348" v14="337666688" v15="1347638609">
                    <CSFeature sxBase="12" syBase="6" wBase="3" hBase="1" />
                </CSWeak>
                <CSWeak weigth="0.754433" v0="1865179208" v1="739191980" v2="1308044323" v3="380971803" v4="419745710" v5="196898563" v6="1099853688" v7="1524452351" v8="2684321753" v9="1946315560" v10="2104831823" v11="725385415" v12="2179116335" v13="3171776451" v14="444481070" v15="1850608274">
                    <CSFeature sxBase="6" syBase="2" wBase="1" hBase="1" />
                </CSWeak>
                <CSWeak weigth="0.726054" v0="573078106" v1="910883402" v2="272517136" v3="3491741950" v4="312729338" v5="35839214" v6="20661517" v7="213311" v8="1962201760" v9="2742167602" v10="331158050" v11="84300704" v12="337790797" v13="139132932" v14="295899352" v15="16777348">
                    <CSFeature sxBase="6" syBase="10" wBase="3" hBase="1" />
                </CSWeak>
                <CSWeak weigth="0.738810" v0="294274656" v1="3869480356" v2="904632058" v3="1061886584" v4="4241126298" v5="265223916" v6="3462876876" v7="2228051881" v8="3385921776" v9="3208786497" v10="3132636105" v11="1911177937" v12="267805659" v13="1725497568" v14="2550074420" v15="1409688198">
                    <CSFeature sxBase="13" syBase="2" wBase="1" hBase="1" />
                </CSWeak>
                <CSWeak weigth="0.746666" v0="1521547472" v1="1055414340" v2="767498035" v3="1778058267" v4="172052560" v5="675599440" v6="873743751" v7="167927695" v8="821219568" v9="1612730880" v10="246759477" v11="440337953" v12="1248018432" v13="1686135300" v14="504759556" v15="251660800">
                    <CSFeature sxBase="0" syBase="7" wBase="3" hBase="1" />
                </CSWeak>
                <CSWeak weigth="0.727593" v0="2922914118" v1="1546382987" v2="1505637732" v3="1720997695" v4="1061054368" v5="1386126667" v6="3023978270" v7="1124583405" v8="2193868931" v9="553935918" v10="3145564344" v11="2340358818" v12="1336095086" v13="1755872000" v14="801628510" v15="97911244">
                    <CSFeature sxBase="17" syBase="16" wBase="1" hBase="1" />
                </CSWeak>
                <CSWeak weigth="0.725547" v0="507128354" v1="50216666" v2="2326668282" v3="2854888040" v4="1078322689" v5="539950637" v6="86143097" v7="1157776415" v8="1623721705" v9="1349535761" v10="2241988658" v11="415499444" v12="88102365" v13="1146422472" v14="88229982" v15="1582502940">
                    <CSFeature sxBase="6" syBase="8" wBase="5" hBase="1" />
                </CSWeak>
            </CSClassificator>
            <CSClassificator threshold="6.804185">
                <CSWeak weigth="0.781720" v0="2048161344" v1="3426110180" v2="515845175" v3="217261887" v4="463130136" v5="646119122" v6="406539535" v7="170727391" v8="404518968" v9="891574275" v10="733308003" v11="108472372" v12="504844352" v13="153635342" v14="524948349" v15="193600078">
                    <CSFeature sxBase="0" syBase="6" wBase="3" hBase="1" />
                </CSWeak>
                <CSWeak weigth="0.856380" v0="1985131624" v1="1916105949" v2="2956952886" v3="757919882" v4="2907999936" v5="4244552488" v6="1276635545" v7="2656897385" v8="3484679960" v9="4062636677" v10="2262757829" v11="2757728938" v12="2921547684" v13="1216859052" v14="1715277034" v15="521221948">
                    <CSFeature sxBase="8" syBase="18" wBase="1" hBase="1" />
                </CSWeak>
                <CSWeak weigth="0.795049" v0="1321618986" v1="817523512" v2="2012545018" v3="2402733808" v4="3988049454" v5="1852194938" v6="2081296235" v7="1062939650" v8="801831594" v9="4043774062" v10="2140169883" v11="2085177146" v12="2319065465" v13="1031961274" v14="377254270" v15="241121806">
                    <CSFeature sxBase="3" syBase="3" wBase="3" hBase="1" />
                </CSWeak>
                <CSWeak weigth="0.819207" v0="971786726" v1="1333483896" v2="2213219815" v3="925433283" v4="3542444016" v5="2119321577" v6="2788659583" v7="1155782623" v8="3904233845" v9="1817315093" v10="2675941879" v11="398413407" v12="1941886919" v13="3249273126" v14="1592667999" v15="1970607501">
                    <CSFeature sxBase="17" syBase="18" wBase="1" hBase="1" />
                </CSWeak>
                <CSWeak weigth="0.842351" v0="1552695416" v1="533568252" v2="2411065275" v3="4214945513" v4="3752265705" v5="2134797148" v6="2279333111" v7="1958655579" v8="4233376841" v9="2330680059" v10="1000330511" v11="1940918240" v12="2845754838" v13="2055717211" v14="1601716030" v15="915019956">
                    <CSFeature sxBase="15" syBase="18" wBase="2" hBase="1" />
                </CSWeak>
                <CSWeak weigth="0.852979" v0="2127178848" v1="2130272961" v2="162379690" v3="3662208320" v4="3114503418" v5="4138433530" v6="4278098314" v7="1664677732" v8="2058331897" v9="1265606212" v10="526348399" v11="715554423" v12="215747131" v13="857581322" v14="1578996222" v15="303738645">
                    <CSFeature sxBase="3" syBase="2" wBase="2" hBase="1" />
                </CSWeak>
                <CSWeak weigth="0.842988" v0="1575494842" v1="4226369268" v2="3486142136" v3="3203905522" v4="1041098816" v5="1207341585" v6="4291808559" v7="1188501303" v8="2833776448" v9="1964469607" v10="1576663907" v11="832040952" v12="1863563648" v13="1359118247" v14="398423417" v15="73932151">
                    <CSFeature sxBase="15" syBase="0" wBase="2" hBase="1" />
                </CSWeak>
                <CSWeak weigth="0.852475" v0="3762203458" v1="1143896632" v2="2712171580" v3="3010838350" v4="2503733482" v5="3213863934" v6="1815142909" v7="268384023" v8="724388275" v9="4259683827" v10="1766571444" v11="1340251025" v12="3061034903" v13="545791997" v14="2553674869" v15="446957031">
                    <CSFeature sxBase="1" syBase="1" wBase="2" hBase="1" />
                </CSWeak>
                <CSWeak weigth="0.879705" v0="1289799912" v1="1610394008" v2="3369907418" v3="3837369420" v4="80774720" v5="1524887730" v6="3321332880" v7="334760454" v8="3228096244" v9="1320865741" v10="3329510404" v11="1436946410" v12="1142604321" v13="1605559035" v14="345112704" v15="343343680">
                    <CSFeature sxBase="8" syBase="14" wBase="1" hBase="2" />
                </CSWeak>
                <CSWeak weigth="0.922951" v0="2436594464" v1="2667177274" v2="3885846506" v3="2129739589" v4="1448601016" v5="660270766" v6="2247228091" v7="1464006261" v8="1312706704" v9="1069254030" v10="2294084570" v11="433613293" v12="3672954610" v13="3215278502" v14="1827171863" v15="209033401">
                    <CSFeature sxBase="14" syBase="1" wBase="1" hBase="1" />
                </CSWeak>
                <CSWeak weigth="0.875724" v0="1635669114" v1="1509541947" v2="1069573176" v3="2083380836" v4="1263072121" v5="459182838" v6="4114586955" v7="1297083365" v8="1901854172" v9="3468031415" v10="2470433759" v11="378510878" v12="3038165303" v13="2924791724" v14="1797207977" v15="1448309653">
                    <CSFeature sxBase="17" syBase="17" wBase="1" hBase="1" />
                </CSWeak>
                <CSWeak weigth="0.900024" v0="3940838730" v1="2008925814" v2="4145998720" v3="3739647391" v4="4091448008" v5="1441732840" v6="1230842694" v7="1329021172" v8="1812394662" v9="3980906756" v10="259118895" v11="2098138047" v12="232734451" v13="151457948" v14="337516478" v15="203111575">
                    <CSFeature sxBase="3" syBase="1" wBase="3" hBase="1" />
                </CSWeak>
                <CSWeak weigth="0.904557" v0="3489579502" v1="4024900573" v2="2877062391" v3="1204884855" v4="2268618848" v5="4093311902" v6="4118757047" v7="2085600255" v8="2121891620" v9="2984364975" v10="2002687481" v11="571960012" v12="2112284708" v13="3291615163" v14="1336934817" v15="1310082286">
                    <CSFeature sxBase="15" syBase="17" wBase="1" hBase="1" />
                </CSWeak>
                <CSWeak weigth="0.907657" v0="1895706800" v1="879473776" v2="1975276955" v3="3605707190" v4="3998116575" v5="225988062" v6="2762727319" v7="1303582307" v8="4210555635" v9="3321059884" v10="3220360179" v11="1803480917" v12="4175355310" v13="1052695854" v14="3251967046" v15="371589965">
                    <CSFeature sxBase="1" syBase="14" wBase="1" hBase="1" />
                </CSWeak>
                <CSWeak weigth="0.902370" v0="951593218" v1="155140056" v2="2771853753" v3="2280594846" v4="3113782298" v5="3713485576" v6="2141078549" v7="2409309230" v8="796355506" v9="2143015526" v10="1702736882" v11="1499398055" v12="2125985584" v13="2058296431" v14="1973238206" v15="1162809161">
                    <CSFeature sxBase="3" syBase="18" wBase="1" hBase="1" />
                </CSWeak>
                <CSWeak weigth="0.949615" v0="1059623024" v1="3756675674" v2="1013334588" v3="1710150399" v4="1593735800" v5="36650744" v6="1392008420" v7="460093151" v8="3203463272" v9="3198041734" v10="1335325908" v11="372973918" v12="2973430961" v13="873362315" v14="2128573946" v15="118162957">
                    <CSFeature sxBase="7" syBase="9" wBase="2" hBase="1" />
                </CSWeak>
                <CSWeak weigth="0.937836" v0="2615192136" v1="4213634606" v2="1853105380" v3="3821627102" v4="4011482232" v5="3621828094" v6="1573353480" v7="1919304993" v8="3046494832" v9="4271791525" v10="2596253159" v11="1434154957" v12="3466325247" v13="2984174581" v14="74673338" v15="51856341">
                    <CSFeature sxBase="4" syBase="14" wBase="1" hBase="1" />
                </CSWeak>
                <CSWeak weigth="0.936962" v0="3971090018" v1="122637596" v2="3489306457" v3="4008899471" v4="3757833872" v5="334950270" v6="3828965231" v7="3882876813" v8="727670294" v9="191758273" v10="3587665639" v11="1179046543" v12="447381848" v13="3560612722" v14="1058796397" v15="406988170">
                    <CSFeature sxBase="16" syBase="14" wBase="1" hBase="1" />
                </CSWeak>
            </CSClassificator>
        </TSCObjectDetector>
    </ILFObjectDetector>
</TLFDetectEngine>
