<?xml version="1.0" ?>
<TLFDetectEngine type="TLFDetectEngine" predictor="TLFAverageNNPredictor">
    <ILFObjectDetector type="TSCObjectDetector">
        <TSCObjectDetector base_width="24" base_height="24" object_type="unknown" detector="ILFObjectDetector">
            <ILFScanner type="TLFScanner" ApertureWidth="24" ApertureHeight="24">
                <TLFParameter type="TLFParameter" m_Value="10.000000" m_MaxValue="100.000000" m_MinValue="1.000000" m_Name="step" m_Descr="step space as a percentage of baseline resolution" />
                <TLFParameter type="TLFParameter" m_Value="1.100000" m_MaxValue="2.000000" m_MinValue="1.100000" m_Name="grow" m_Descr="step on the scale" />
                <TLFParameter type="TLFParameter" m_Value="1.000000" m_MaxValue="4.000000" m_MinValue="1.000000" m_Name="MinSize" m_Descr="min size of scanned object in the BaseWidth" />
                <TLFParameter type="TLFParameter" m_Value="50.000000" m_MaxValue="100.000000" m_MinValue="1.000000" m_Name="MaxSize" m_Descr="max size of scanned object in the BaseWidth" />
            </ILFScanner>
            <CSClassificator threshold="2.546797">
                <CSWeak weigth="3.001269" v0="24768" v1="0" v2="0" v3="0" v4="32" v5="0" v6="16" v7="0" v8="866" v9="0" v10="32" v11="16777216" v12="8819" v13="2" v14="65975" v15="1359020291">
                    <CSFeature sxBase="0" syBase="3" wBase="7" hBase="3" />
                </CSWeak>
                <CSWeak weigth="2.636187" v0="4223200" v1="8405184" v2="64" v3="0" v4="4202608" v5="0" v6="1048656" v7="0" v8="1574496" v9="33554432" v10="80" v11="0" v12="4416503" v13="1" v14="115" v15="1">
                    <CSFeature sxBase="0" syBase="8" wBase="6" hBase="3" />
                </CSWeak>
                <CSWeak weigth="2.546797" v0="1111554752" v1="28672" v2="58128" v3="4096" v4="41536" v5="0" v6="0" v7="0" v8="4225914" v9="8192" v10="8746" v11="0" v12="131603" v13="3" v14="73735" v15="257">
                    <CSFeature sxBase="6" syBase="5" wBase="5" hBase="3" />
                </CSWeak>
            </CSClassificator>
            <CSClassificator threshold="3.715474">
                <CSWeak weigth="2.353251" v0="1073795264" v1="8405184" v2="53440" v3="20672" v4="0" v5="0" v6="8192" v7="0" v8="20544" v9="0" v10="8192" v11="0" v12="20560" v13="0" v14="48" v15="0">
                    <CSFeature sxBase="6" syBase="9" wBase="5" hBase="4" />
                </CSWeak>
                <CSWeak weigth="2.007181" v0="2097152" v1="2097160" v2="8388912" v3="524576" v4="3424272" v5="33619968" v6="262227" v7="16842752" v8="4194403" v9="16777216" v10="16908322" v11="593923" v12="66935" v13="8912896" v14="285541655" v15="17105153">
                    <CSFeature sxBase="0" syBase="4" wBase="6" hBase="2" />
                </CSWeak>
                <CSWeak weigth="1.917203" v0="36731512" v1="2768874" v2="122716154" v3="2888490" v4="704690746" v5="305827502" v6="656656" v7="5242914" v8="1080779298" v9="1243614248" v10="544916022" v11="3801090" v12="36896803" v13="33838336" v14="8195" v15="32">
                    <CSFeature sxBase="8" syBase="9" wBase="4" hBase="2" />
                </CSWeak>
                <CSWeak weigth="1.810030" v0="1431097544" v1="353399298" v2="289408072" v3="1360042256" v4="1437231118" v5="1460342794" v6="1147077771" v7="1364262918" v8="273961320" v9="1426093221" v10="1359051758" v11="1460737927" v12="3309782846" v13="1409699973" v14="1162282035" v15="85414213">
                    <CSFeature sxBase="0" syBase="0" wBase="7" hBase="2" />
                </CSWeak>
                <CSWeak weigth="1.905445" v0="268499690" v1="69913162" v2="19813098" v3="36306978" v4="36213280" v5="167838208" v6="3670315" v7="262148" v8="37896746" v9="704643072" v10="11141563" v11="143904" v12="2233143" v13="1107296257" v14="591671" v15="65537">
                    <CSFeature sxBase="0" syBase="7" wBase="7" hBase="2" />
                </CSWeak>
            </CSClassificator>
            <CSClassificator threshold="4.529695">
                <CSWeak weigth="2.152690" v0="20672" v1="8929472" v2="20672" v3="16576" v4="0" v5="0" v6="4096" v7="0" v8="0" v9="2697740288" v10="0" v11="0" v12="0" v13="2147491840" v14="0" v15="0">
                    <CSFeature sxBase="6" syBase="12" wBase="5" hBase="3" />
                </CSWeak>
                <CSWeak weigth="1.603378" v0="6320352" v1="16448" v2="8448" v3="0" v4="10490416" v5="0" v6="48" v7="0" v8="28992" v9="2" v10="8704" v11="0" v12="173939" v13="0" v14="35" v15="0">
                    <CSFeature sxBase="0" syBase="6" wBase="7" hBase="3" />
                </CSWeak>
                <CSWeak weigth="1.564991" v0="1111519936" v1="21378" v2="1895887808" v3="4160" v4="4608" v5="0" v6="4672" v7="0" v8="31552" v9="47104" v10="6656" v11="61952" v12="35378" v13="4130" v14="8738" v15="64">
                    <CSFeature sxBase="9" syBase="8" wBase="4" hBase="3" />
                </CSWeak>
                <CSWeak weigth="1.488990" v0="1141928032" v1="335561664" v2="356515976" v3="285278992" v4="398713388" v5="1411399809" v6="12910677" v7="286326788" v8="1355043944" v9="1962938376" v10="1342261828" v11="1392601860" v12="1163739172" v13="1359217672" v14="1091896849" v15="16847104">
                    <CSFeature sxBase="0" syBase="1" wBase="6" hBase="2" />
                </CSWeak>
                <CSWeak weigth="1.632453" v0="536934952" v1="2276906" v2="1665171314" v3="564661034" v4="671754752" v5="43560" v6="274" v7="2086" v8="271788651" v9="1092130" v10="305136434" v11="12274986" v12="6492979" v13="272451" v14="268700195" v15="33">
                    <CSFeature sxBase="9" syBase="8" wBase="4" hBase="2" />
                </CSWeak>
                <CSWeak weigth="1.480128" v0="540812848" v1="1074012786" v2="1358694198" v3="1442055072" v4="685695570" v5="15491174" v6="1181484052" v7="653533730" v8="1351274820" v9="2358046468" v10="1474782979" v11="1112677409" v12="2080300309" v13="1525582320" v14="1089208320" v15="73670690">
                    <CSFeature sxBase="6" syBase="9" wBase="4" hBase="1" />
                </CSWeak>
                <CSWeak weigth="1.560577" v0="20672" v1="8405120" v2="16576" v3="64" v4="16448" v5="0" v6="64" v7="0" v8="28736" v9="0" v10="0" v11="0" v12="12881" v13="0" v14="8305" v15="0">
                    <CSFeature sxBase="0" syBase="7" wBase="7" hBase="4" />
                </CSWeak>
            </CSClassificator>
            <CSClassificator threshold="3.945067">
                <CSWeak weigth="1.824451" v0="524288" v1="12582976" v2="64" v3="64" v4="67108864" v5="4734976" v6="0" v7="0" v8="8192" v9="2160329408" v10="0" v11="0" v12="2833776640" v13="2901196960" v14="0" v15="0">
                    <CSFeature sxBase="0" syBase="15" wBase="7" hBase="2" />
                </CSWeak>
                <CSWeak weigth="1.431810" v0="24576" v1="0" v2="16785408" v3="0" v4="0" v5="0" v6="0" v7="0" v8="43552" v9="0" v10="0" v11="0" v12="2594" v13="8192" v14="12291" v15="65537">
                    <CSFeature sxBase="9" syBase="3" wBase="4" hBase="3" />
                </CSWeak>
                <CSWeak weigth="1.333897" v0="705723200" v1="4288" v2="322985456" v3="1049860" v4="2696" v5="0" v6="16781653" v7="0" v8="29256" v9="54016" v10="5247563" v11="16" v12="0" v13="16896" v14="131328" v15="0">
                    <CSFeature sxBase="12" syBase="11" wBase="3" hBase="2" />
                </CSWeak>
                <CSWeak weigth="1.260651" v0="1073741888" v1="285233216" v2="83886080" v3="286261248" v4="83918856" v5="268500992" v6="16" v7="786688" v8="131072" v9="268439552" v10="135168" v11="16777220" v12="4456541" v13="268435584" v14="65541" v15="65793">
                    <CSFeature sxBase="0" syBase="3" wBase="6" hBase="2" />
                </CSWeak>
                <CSWeak weigth="1.207662" v0="4210880" v1="8405184" v2="16448" v3="0" v4="64" v5="0" v6="0" v7="0" v8="16448" v9="3221225472" v10="0" v11="0" v12="4194516" v13="0" v14="16" v15="0">
                    <CSFeature sxBase="0" syBase="10" wBase="6" hBase="3" />
                </CSWeak>
                <CSWeak weigth="1.277876" v0="1620182064" v1="1073758210" v2="1079395618" v3="1549012392" v4="268448402" v5="12845104" v6="1076887552" v7="1936851378" v8="4062475524" v9="2298669792" v10="2138293528" v11="1346651140" v12="269538653" v13="147597545" v14="524288" v15="83173427">
                    <CSFeature sxBase="9" syBase="9" wBase="3" hBase="1" />
                </CSWeak>
                <CSWeak weigth="1.200436" v0="1366585416" v1="355033088" v2="161480936" v3="1396781824" v4="2502426830" v5="1091764386" v6="136609923" v7="151060480" v8="361023216" v9="19333253" v10="134883977" v11="1095762423" v12="1784808144" v13="1108345094" v14="153690644" v15="17105749">
                    <CSFeature sxBase="2" syBase="0" wBase="5" hBase="2" />
                </CSWeak>
                <CSWeak weigth="1.350519" v0="708864832" v1="22528" v2="855662016" v3="16384" v4="2112" v5="512" v6="8706" v7="2" v8="167836256" v9="32784" v10="32770" v11="0" v12="134220550" v13="16392" v14="8714" v15="1">
                    <CSFeature sxBase="9" syBase="7" wBase="4" hBase="3" />
                </CSWeak>
                <CSWeak weigth="1.223468" v0="1779983970" v1="1079255130" v2="1557140791" v3="4115998001" v4="2720025202" v5="12845168" v6="1885733418" v7="1987314224" v8="3538104112" v9="1141795974" v10="1357667074" v11="1358692386" v12="177016116" v13="1078772960" v14="1409810688" v15="41156656">
                    <CSFeature sxBase="9" syBase="10" wBase="3" hBase="1" />
                </CSWeak>
            </CSClassificator>
            <CSClassificator threshold="4.726545">
                <CSWeak weigth="1.332632" v0="64" v1="2155872448" v2="240" v3="64" v4="2214625280" v5="2759884800" v6="20816" v7="0" v8="1073766464" v9="3230138368" v10="1048592" v11="0" v12="176422912" v13="3263197312" v14="0" v15="0">
                    <CSFeature sxBase="12" syBase="15" wBase="3" hBase="2" />
                </CSWeak>
                <CSWeak weigth="1.174221" v0="1088438312" v1="216268800" v2="10485760" v3="15204352" v4="162" v5="8388736" v6="278921268" v7="2097156" v8="552075380" v9="9043968" v10="15335439" v11="6422656" v12="1074484703" v13="524296" v14="2360325" v15="65793">
                    <CSFeature sxBase="0" syBase="5" wBase="6" hBase="2" />
                </CSWeak>
                <CSWeak weigth="1.097881" v0="1950102128" v1="1176505920" v2="1966479250" v3="1987120946" v4="343468784" v5="568910560" v6="3407922" v7="821821984" v8="4246492420" v9="2190094280" v10="2130140487" v11="1416528904" v12="1219714341" v13="787382700" v14="139264" v15="40108070">
                    <CSFeature sxBase="6" syBase="10" wBase="4" hBase="1" />
                </CSWeak>
                <CSWeak weigth="1.081928" v0="1392562688" v1="318767104" v2="3498082496" v3="1358970880" v4="50354752" v5="67108864" v6="1342226432" v7="0" v8="1669370368" v9="2048" v10="302039560" v11="1024" v12="704699136" v13="0" v14="805485066" v15="0">
                    <CSFeature sxBase="15" syBase="5" wBase="2" hBase="4" />
                </CSWeak>
                <CSWeak weigth="1.115173" v0="1413509184" v1="1426064456" v2="142615684" v3="419512320" v4="3223322752" v5="289472512" v6="151519232" v7="302055424" v8="67373056" v9="1073758464" v10="301989892" v11="16842848" v12="4160" v13="268435520" v14="16843013" v15="16843017">
                    <CSFeature sxBase="0" syBase="2" wBase="5" hBase="2" />
                </CSWeak>
                <CSWeak weigth="1.228780" v0="3175024" v1="67111520" v2="372447219" v3="808455474" v4="2166227696" v5="36184674" v6="3179286" v7="3162210" v8="4096" v9="235408960" v10="2151887120" v11="136315904" v12="168297472" v13="369789440" v14="268574752" v15="131106">
                    <CSFeature sxBase="6" syBase="12" wBase="5" hBase="1" />
                </CSWeak>
                <CSWeak weigth="1.088650" v0="1088966904" v1="187334664" v2="586154114" v3="183435306" v4="2216706080" v5="1982513152" v6="4325400" v7="0" v8="1592152128" v9="539099136" v10="4458044" v11="5111840" v12="1077282495" v13="17317920" v14="17372677" v15="65792">
                    <CSFeature sxBase="0" syBase="6" wBase="6" hBase="2" />
                </CSWeak>
                <CSWeak weigth="1.104520" v0="1116865026" v1="136315456" v2="4126019435" v3="2012611120" v4="539025952" v5="3769123490" v6="346032240" v7="820117538" v8="1376277764" v9="167780864" v10="3573106486" v11="1075840038" v12="1083886917" v13="2359340289" v14="268436482" v15="1638497">
                    <CSFeature sxBase="6" syBase="9" wBase="5" hBase="1" />
                </CSWeak>
                <CSWeak weigth="1.100005" v0="84951248" v1="2224313536" v2="546528" v3="287326372" v4="408686700" v5="2559590432" v6="201416704" v7="69285504" v8="1754566672" v9="3636871872" v10="8978504" v11="71303682" v12="1645084696" v13="4260163716" v14="33822786" v15="50475008">
                    <CSFeature sxBase="0" syBase="15" wBase="4" hBase="1" />
                </CSWeak>
                <CSWeak weigth="1.154318" v0="1086857234" v1="1448387144" v2="1414599046" v3="3572502530" v4="3392012854" v5="1089872294" v6="348389506" v7="1383207330" v8="3691375908" v9="1254682336" v10="1950892064" v11="1077953619" v12="1873863940" v13="1122930152" v14="339808426" v15="394002980">
                    <CSFeature sxBase="7" syBase="8" wBase="3" hBase="1" />
                </CSWeak>
                <CSWeak weigth="1.098114" v0="1854579234" v1="10504714" v2="1957298850" v3="1692819616" v4="621342539" v5="1219118082" v6="17441792" v7="11014144" v8="1082803534" v9="524288" v10="1155954423" v11="75760647" v12="548177" v13="17891617" v14="470539" v15="85787713">
                    <CSFeature sxBase="0" syBase="7" wBase="7" hBase="1" />
                </CSWeak>
                <CSWeak weigth="1.108455" v0="542122096" v1="273425992" v2="1349715222" v3="1916274486" v4="3229153874" v5="6422640" v6="36897578" v7="2012222258" v8="3864294928" v9="1359899460" v10="1358108119" v11="1342506276" v12="1357463949" v13="237822180" v14="8650752" v15="4194866">
                    <CSFeature sxBase="10" syBase="11" wBase="3" hBase="1" />
                </CSWeak>
            </CSClassificator>
            <CSClassificator threshold="6.036706">
                <CSWeak weigth="1.122949" v0="1073754144" v1="286326784" v2="4098" v3="16777216" v4="268435456" v5="1191182336" v6="16777232" v7="16777216" v8="2228256" v9="16777216" v10="1048610" v11="1091584000" v12="8995" v13="16777219" v14="65539" v15="16842769">
                    <CSFeature sxBase="6" syBase="3" wBase="5" hBase="2" />
                </CSWeak>
                <CSWeak weigth="1.109044" v0="16576" v1="8388800" v2="192" v3="0" v4="64" v5="0" v6="0" v7="0" v8="134217792" v9="2097152" v10="0" v11="0" v12="80" v13="0" v14="16" v15="0">
                    <CSFeature sxBase="1" syBase="11" wBase="6" hBase="3" />
                </CSWeak>
                <CSWeak weigth="1.118071" v0="134246464" v1="20768" v2="268456064" v3="36864" v4="41040" v5="0" v6="0" v7="0" v8="2140712" v9="143488" v10="2056" v11="40960" v12="2586" v13="8256" v14="2050" v15="8192">
                    <CSFeature sxBase="9" syBase="6" wBase="4" hBase="3" />
                </CSWeak>
                <CSWeak weigth="1.034874" v0="25090" v1="1145348106" v2="1919558922" v3="1902251434" v4="2380322" v5="1080033834" v6="1348481058" v7="1920148018" v8="4279367429" v9="1284044000" v10="2069840148" v11="1142162736" v12="1149300097" v13="1894539684" v14="4595744" v15="1343504496">
                    <CSFeature sxBase="9" syBase="8" wBase="3" hBase="1" />
                </CSWeak>
                <CSWeak weigth="0.989387" v0="262152" v1="12599360" v2="2360386" v3="64" v4="262144" v5="138563652" v6="1078067201" v7="72351936" v8="75513860" v9="3873444344" v10="71303808" v11="138412045" v12="1613235716" v13="4041347160" v14="1074659332" v15="285216768">
                    <CSFeature sxBase="2" syBase="17" wBase="5" hBase="1" />
                </CSWeak>
                <CSWeak weigth="1.007898" v0="1347187816" v1="491784824" v2="16448" v3="319854656" v4="1082196034" v5="84811844" v6="2181597185" v7="85983242" v8="214749664" v9="1401118852" v10="1128272804" v11="1427113348" v12="3321900020" v13="270664064" v14="151536916" v15="83956507">
                    <CSFeature sxBase="0" syBase="0" wBase="6" hBase="2" />
                </CSWeak>
                <CSWeak weigth="1.013192" v0="1077695024" v1="1208624208" v2="1442579840" v3="1509721380" v4="573632624" v5="7147632" v6="1145308192" v7="1887187064" v8="1152708864" v9="219016876" v10="1458836561" v11="1478256290" v12="918288244" v13="175022500" v14="1074536450" v15="376701041">
                    <CSFeature sxBase="7" syBase="11" wBase="3" hBase="1" />
                </CSWeak>
                <CSWeak weigth="0.996398" v0="0" v1="12583104" v2="4214864" v3="80" v4="213909504" v5="1073741824" v6="4210688" v7="4096" v8="2148024320" v9="3773827784" v10="64" v11="0" v12="12591104" v13="4042453128" v14="0" v15="512">
                    <CSFeature sxBase="9" syBase="15" wBase="4" hBase="2" />
                </CSWeak>
                <CSWeak weigth="1.089030" v0="1174405120" v1="1075847200" v2="1903300640" v3="4065722370" v4="67109410" v5="6316578" v6="2113570" v7="871776882" v8="4110474501" v9="1074592288" v10="1966359824" v11="1081114752" v12="1342763276" v13="279186080" v14="1141113860" v15="286658594">
                    <CSFeature sxBase="9" syBase="7" wBase="3" hBase="1" />
                </CSWeak>
                <CSWeak weigth="1.003158" v0="167801344" v1="53280" v2="1895886912" v3="20480" v4="41032" v5="0" v6="2" v7="0" v8="52744" v9="59616" v10="16392" v11="4224" v12="34818" v13="0" v14="2063" v15="65601">
                    <CSFeature sxBase="9" syBase="5" wBase="4" hBase="3" />
                </CSWeak>
                <CSWeak weigth="1.046264" v0="1083834914" v1="1148251656" v2="1902781728" v3="1682062194" v4="3786793632" v5="4072976546" v6="1615987754" v7="821428834" v8="479261952" v9="478965408" v10="4096097655" v11="1342203490" v12="194641725" v13="3270385704" v14="336115590" v15="38031476">
                    <CSFeature sxBase="5" syBase="8" wBase="4" hBase="1" />
                </CSWeak>
                <CSWeak weigth="1.045427" v0="335589984" v1="76153570" v2="1975394290" v3="1893859386" v4="2444916314" v5="2834080418" v6="281298032" v7="385613856" v8="3372373249" v9="210382464" v10="1207161205" v11="271646722" v12="2583061829" v13="4018858025" v14="812389632" v15="10747936">
                    <CSFeature sxBase="5" syBase="11" wBase="5" hBase="1" />
                </CSWeak>
                <CSWeak weigth="1.041689" v0="353956866" v1="2356187712" v2="3381200256" v3="2227372288" v4="289931264" v5="939524245" v6="2769932495" v7="72417904" v8="168044568" v9="202178816" v10="33567493" v11="370251061" v12="890798917" v13="67436802" v14="152896309" v15="287386885">
                    <CSFeature sxBase="0" syBase="4" wBase="3" hBase="1" />
                </CSWeak>
                <CSWeak weigth="1.004991" v0="1087916034" v1="1111492296" v2="1942095256" v3="1919993623" v4="36982834" v5="75629154" v6="1322274" v7="1911947618" v8="1358013456" v9="1309601380" v10="1970306325" v11="1551111313" v12="719822135" v13="167741682" v14="524834" v15="41156787">
                    <CSFeature sxBase="9" syBase="11" wBase="3" hBase="1" />
                </CSWeak>
            </CSClassificator>
            <CSClassificator threshold="6.820891">
                <CSWeak weigth="1.017772" v0="855658496" v1="0" v2="1342177280" v3="0" v4="301993984" v5="0" v6="8192" v7="0" v8="989884416" v9="0" v10="134242304" v11="0" v12="234945024" v13="0" v14="33618443" v15="1">
                    <CSFeature sxBase="12" syBase="2" wBase="3" hBase="4" />
                </CSWeak>
                <CSWeak weigth="0.971242" v0="1107304994" v1="268444194" v2="1969622306" v3="1920074274" v4="2239018" v5="35807778" v6="539427874" v7="846274850" v8="3556963588" v9="1073759488" v10="2139060023" v11="1073873925" v12="2147679492" v13="1073751296" v14="272630784" v15="341070880">
                    <CSFeature sxBase="9" syBase="7" wBase="4" hBase="1" />
                </CSWeak>
                <CSWeak weigth="1.009332" v0="571499072" v1="8390848" v2="47240656" v3="5968" v4="67108864" v5="0" v6="37184" v7="0" v8="1074851840" v9="1621623296" v10="3149904" v11="0" v12="532480" v13="1073872896" v14="0" v15="0">
                    <CSFeature sxBase="9" syBase="13" wBase="4" hBase="2" />
                </CSWeak>
                <CSWeak weigth="1.019189" v0="1076392466" v1="1342758960" v2="1081869744" v3="1348013112" v4="409661554" v5="32375344" v6="1346371616" v7="1391460984" v8="3388666900" v9="3289181735" v10="1551324176" v11="416553772" v12="1184562433" v13="852361460" v14="7365188" v15="273945214">
                    <CSFeature sxBase="8" syBase="11" wBase="3" hBase="1" />
                </CSWeak>
                <CSWeak weigth="0.967504" v0="1427666120" v1="822083648" v2="524352" v3="20971521" v4="1084281494" v5="1896546312" v6="1141378277" v7="1342194688" v8="1082131624" v9="3573598664" v10="285226660" v11="352323354" v12="2329675920" v13="83886284" v14="202117300" v15="85263633">
                    <CSFeature sxBase="3" syBase="0" wBase="6" hBase="2" />
                </CSWeak>
                <CSWeak weigth="0.954945" v0="1922576434" v1="1176560754" v2="1901667611" v3="1517559067" v4="3602576112" v5="14895714" v6="1417937570" v7="1425482354" v8="3069736212" v9="1846472196" v10="1819825433" v11="1411137604" v12="1756552985" v13="183409120" v14="1611669504" v15="7348337">
                    <CSFeature sxBase="8" syBase="10" wBase="3" hBase="1" />
                </CSWeak>
                <CSWeak weigth="1.006464" v0="71303168" v1="4194816" v2="4195328" v3="1077936640" v4="1073750532" v5="277217296" v6="1310720" v7="2097152" v8="4260352" v9="79839436" v10="134513024" v11="32768" v12="2282245632" v13="2230075584" v14="138690624" v15="2">
                    <CSFeature sxBase="3" syBase="18" wBase="6" hBase="1" />
                </CSWeak>
                <CSWeak weigth="0.975906" v0="1446511122" v1="3426805280" v2="1885216770" v3="1909048098" v4="2302161010" v5="675817696" v6="337184774" v7="821306224" v8="4017419537" v9="449769096" v10="2020720900" v11="1498065954" v12="1793785157" v13="49196256" v14="269221888" v15="376709224">
                    <CSFeature sxBase="7" syBase="9" wBase="3" hBase="1" />
                </CSWeak>
                <CSWeak weigth="0.970713" v0="4256448" v1="4096" v2="1090580736" v3="268440000" v4="16928" v5="0" v6="0" v7="0" v8="4335168" v9="8192" v10="514" v11="16" v12="1049238" v13="2" v14="35" v15="1">
                    <CSFeature sxBase="6" syBase="6" wBase="5" hBase="3" />
                </CSWeak>
                <CSWeak weigth="0.944135" v0="544735282" v1="1142432960" v2="1725695385" v3="1347981078" v4="2726187728" v5="10617072" v6="8389376" v7="1383334960" v8="1220026384" v9="3324961796" v10="301028625" v11="75798797" v12="717103140" v13="430874784" v14="540811280" v15="5767280">
                    <CSFeature sxBase="8" syBase="12" wBase="3" hBase="1" />
                </CSWeak>
                <CSWeak weigth="0.992989" v0="1485484658" v1="211848770" v2="398071794" v3="1743926898" v4="3163066448" v5="715712610" v6="80151634" v7="268959744" v8="555806722" v9="209717952" v10="1440958255" v11="1108084802" v12="791211285" v13="2324242689" v14="5048066" v15="66048">
                    <CSFeature sxBase="3" syBase="10" wBase="6" hBase="1" />
                </CSWeak>
                <CSWeak weigth="0.943936" v0="1983406834" v1="3465452154" v2="1475216688" v3="4157898976" v4="2939879162" v5="686597666" v6="1354956984" v7="99370082" v8="2825544992" v9="1258834312" v10="1640164815" v11="106841664" v12="682286381" v13="144648449" v14="11297800" v15="101453124">
                    <CSFeature sxBase="0" syBase="8" wBase="6" hBase="1" />
                </CSWeak>
                <CSWeak weigth="0.966557" v0="1610642546" v1="549470432" v2="291288" v3="625166912" v4="2485383264" v5="2215678088" v6="335773248" v7="33571465" v8="3456118848" v9="3772026946" v10="2113737" v11="33556096" v12="2855123210" v13="1133153224" v14="169308697" v15="118165765">
                    <CSFeature sxBase="0" syBase="14" wBase="4" hBase="1" />
                </CSWeak>
                <CSWeak weigth="0.977775" v0="1353740896" v1="1377484888" v2="3762291733" v3="4127088009" v4="337119936" v5="1371537472" v6="843580171" v7="510871331" v8="2098789252" v9="184543211" v10="1559777298" v11="1398886517" v12="58770505" v13="46743792" v14="268435994" v15="282263602">
                    <CSFeature sxBase="12" syBase="10" wBase="2" hBase="1" />
                </CSWeak>
                <CSWeak weigth="0.982550" v0="192" v1="3229614280" v2="1048770" v3="7340096" v4="67108864" v5="3229646976" v6="1053043" v7="17" v8="2717917184" v9="2659731488" v10="1048640" v11="4194304" v12="2550270064" v13="3781705776" v14="16778500" v15="0">
                    <CSFeature sxBase="15" syBase="15" wBase="2" hBase="2" />
                </CSWeak>
                <CSWeak weigth="1.043534" v0="1616389136" v1="541614112" v2="1423049891" v3="4032038819" v4="4215330" v5="11804722" v6="69602858" v7="561054627" v8="3565213012" v9="1602289326" v10="1916671808" v11="67110305" v12="439934540" v13="234751656" v14="524" v15="282079264">
                    <CSFeature sxBase="9" syBase="9" wBase="3" hBase="1" />
                </CSWeak>
            </CSClassificator>
            <CSClassificator threshold="5.567774">
                <CSWeak weigth="1.052850" v0="643956762" v1="3360203296" v2="3561817344" v3="4051027120" v4="1848441074" v5="1711145578" v6="1364852978" v7="1542983794" v8="3400584516" v9="462876006" v10="4031829312" v11="475621472" v12="707452749" v13="133112297" v14="341582370" v15="1079967841">
                    <CSFeature sxBase="6" syBase="9" wBase="3" hBase="1" />
                </CSWeak>
                <CSWeak weigth="1.047306" v0="1950250104" v1="1693098826" v2="1476265656" v3="3654339499" v4="2545541851" v5="2933842152" v6="1979586652" v7="1390149872" v8="1340667316" v9="1309339496" v10="1560018213" v11="1435896370" v12="1119024976" v13="250538408" v14="515518570" v15="40763497">
                    <CSFeature sxBase="4" syBase="10" wBase="4" hBase="1" />
                </CSWeak>
                <CSWeak weigth="1.065438" v0="1972524232" v1="1436127448" v2="227295232" v3="1363742992" v4="377290888" v5="3271639240" v6="13097806" v7="357634128" v8="25474276" v9="3581218041" v10="274754032" v11="1158959228" v12="2168883152" v13="16798848" v14="85671969" v15="286851073">
                    <CSFeature sxBase="9" syBase="0" wBase="4" hBase="2" />
                </CSWeak>
                <CSWeak weigth="1.112038" v0="1549275760" v1="1918425100" v2="1981441413" v3="1951530382" v4="1059860562" v5="1232609872" v6="352937166" v7="1366648370" v8="4067996242" v9="2075033544" v10="1753048402" v11="408901054" v12="3086481473" v13="382370292" v14="537407530" v15="276563831">
                    <CSFeature sxBase="10" syBase="11" wBase="2" hBase="1" />
                </CSWeak>
                <CSWeak weigth="1.096634" v0="1149248032" v1="1415602208" v2="1952580640" v3="4101111858" v4="67108864" v5="1097736930" v6="2432106634" v7="1366700922" v8="4282705173" v9="3529305729" v10="2136863060" v11="1566585132" v12="1212538351" v13="1692198897" v14="286265862" v15="357057663">
                    <CSFeature sxBase="8" syBase="7" wBase="3" hBase="1" />
                </CSWeak>
                <CSWeak weigth="1.122103" v0="1039988456" v1="4183873432" v2="1174174722" v3="4128551327" v4="490687104" v5="3716592761" v6="4290367331" v7="890961999" v8="3378046104" v9="2762865124" v10="2655866189" v11="4215930859" v12="1341721546" v13="499266750" v14="253298281" v15="588710707">
                    <CSFeature sxBase="2" syBase="0" wBase="3" hBase="1" />
                </CSWeak>
                <CSWeak weigth="1.117728" v0="1303034416" v1="246189802" v2="4159590387" v3="2113348658" v4="3198320264" v5="3266063082" v6="1710769554" v7="83755056" v8="3274342671" v9="1074422026" v10="938866015" v11="606668864" v12="789429045" v13="161022265" v14="43922187" v15="121569326">
                    <CSFeature sxBase="3" syBase="9" wBase="6" hBase="1" />
                </CSWeak>
                <CSWeak weigth="1.137127" v0="1738689224" v1="1934177955" v2="653991806" v3="2656104579" v4="1966790432" v5="3283236830" v6="3849160738" v7="2001127269" v8="3756536969" v9="3373636999" v10="293297651" v11="1176040863" v12="1416836726" v13="2061832138" v14="1446697891" v15="89079716">
                    <CSFeature sxBase="0" syBase="1" wBase="2" hBase="1" />
                </CSWeak>
                <CSWeak weigth="1.113583" v0="3874776096" v1="3456655474" v2="1899537854" v3="1433418280" v4="3390347874" v5="158073414" v6="1442709506" v7="1400185136" v8="2096026972" v9="2368403239" v10="2145122137" v11="1515603260" v12="1673527181" v13="799969253" v14="386663542" v15="326316599">
                    <CSFeature sxBase="8" syBase="9" wBase="3" hBase="1" />
                </CSWeak>
                <CSWeak weigth="1.146799" v0="1188675040" v1="2596467195" v2="4235622175" v3="1490499231" v4="2124411289" v5="3807359797" v6="2130872217" v7="2458430188" v8="4059375139" v9="4072734174" v10="1775238077" v11="700822775" v12="918727181" v13="3632781022" v14="726357648" v15="230765103">
                    <CSFeature sxBase="7" syBase="18" wBase="1" hBase="1" />
                </CSWeak>
                <CSWeak weigth="1.136815" v0="2333274740" v1="1039290088" v2="3353466602" v3="3841463532" v4="1979015352" v5="1381602698" v6="939917347" v7="1057763702" v8="2628740880" v9="475775749" v10="3512430799" v11="470818674" v12="420203417" v13="195108593" v14="458979231" v15="223414639">
                    <CSFeature sxBase="0" syBase="3" wBase="1" hBase="1" />
                </CSWeak>
                <CSWeak weigth="1.144951" v0="1391230508" v1="912536232" v2="1429484027" v3="366268418" v4="3094143785" v5="3413645467" v6="3223381996" v7="345852197" v8="3367390808" v9="2612772068" v10="1433730639" v11="1194455499" v12="248990024" v13="87107567" v14="337209117" v15="17645875">
                    <CSFeature sxBase="2" syBase="0" wBase="6" hBase="1" />
                </CSWeak>
                <CSWeak weigth="1.123675" v0="1791500346" v1="2090268266" v2="1148602358" v3="3756522738" v4="1925175410" v5="1025646728" v6="301933650" v7="1424233018" v8="3886268405" v9="3613175798" v10="1471792529" v11="1585274674" v12="1455355717" v13="1313860340" v14="105132578" v15="72225400">
                    <CSFeature sxBase="7" syBase="10" wBase="3" hBase="1" />
                </CSWeak>
            </CSClassificator>
            <CSClassificator threshold="4.826457">
                <CSWeak weigth="1.466190" v0="3120626176" v1="53504" v2="4076926976" v3="20480" v4="134253056" v5="4096" v6="268443648" v7="0" v8="704707072" v9="12322" v10="167799296" v11="136" v12="134412842" v13="640" v14="10794" v15="12320">
                    <CSFeature sxBase="12" syBase="6" wBase="3" hBase="3" />
                </CSWeak>
                <CSWeak weigth="1.102571" v0="20994" v1="4104" v2="838877184" v3="16384" v4="2" v5="0" v6="0" v7="0" v8="64064" v9="0" v10="16779272" v11="0" v12="27210" v13="32768" v14="10242" v15="16842753">
                    <CSFeature sxBase="9" syBase="4" wBase="4" hBase="3" />
                </CSWeak>
                <CSWeak weigth="1.034301" v0="268456048" v1="4194384" v2="7542069" v3="2098975" v4="4160" v5="2147483712" v6="33572609" v7="536876801" v8="1345589264" v9="48464064" v10="24196529" v11="1048834" v12="692322320" v13="2427457664" v14="536870980" v15="0">
                    <CSFeature sxBase="12" syBase="15" wBase="3" hBase="1" />
                </CSWeak>
                <CSWeak weigth="1.008544" v0="1879058432" v1="1879068736" v2="1929433088" v3="1934706180" v4="526850" v5="1430257664" v6="1077420042" v7="2068906768" v8="387050759" v9="16648" v10="1207988262" v11="1090782210" v12="1346389534" v13="17303552" v14="10242" v15="321933362">
                    <CSFeature sxBase="13" syBase="8" wBase="2" hBase="1" />
                </CSWeak>
                <CSWeak weigth="0.944924" v0="4193172652" v1="4294210536" v2="1414578320" v3="1435519960" v4="3488343176" v5="288948384" v6="2423259440" v7="1431372544" v8="3368864808" v9="3071396032" v10="205792544" v11="353615972" v12="84427608" v13="1114116" v14="2425017" v15="336941841">
                    <CSFeature sxBase="3" syBase="1" wBase="6" hBase="1" />
                </CSWeak>
                <CSWeak weigth="0.950322" v0="771813440" v1="167821408" v2="1359012480" v3="33562880" v4="2197862408" v5="16777280" v6="285270240" v7="16777216" v8="2281765384" v9="28672" v10="553708040" v11="384" v12="33597738" v13="16386" v14="14858" v15="34">
                    <CSFeature sxBase="15" syBase="7" wBase="2" hBase="3" />
                </CSWeak>
                <CSWeak weigth="0.908528" v0="269646418" v1="9700080" v2="871716281" v3="1450184459" v4="2148581618" v5="13647936" v6="34621184" v7="536876801" v8="1592830544" v9="3503156616" v10="7817587" v11="70192411" v12="271589400" v13="12583586" v14="2245648" v15="2">
                    <CSFeature sxBase="11" syBase="13" wBase="3" hBase="1" />
                </CSWeak>
                <CSWeak weigth="0.932099" v0="882915938" v1="1122257058" v2="1395147266" v3="1458858498" v4="598737710" v5="1250476770" v6="343941160" v7="296288304" v8="3248647578" v9="134219776" v10="1885763021" v11="1141964802" v12="2150223625" v13="177740033" v14="17507343" v15="1469841412">
                    <CSFeature sxBase="1" syBase="8" wBase="6" hBase="1" />
                </CSWeak>
                <CSWeak weigth="0.899193" v0="2088794162" v1="1787480652" v2="1275219076" v3="1552957834" v4="2000744528" v5="1080574034" v6="273943320" v7="1349533985" v8="2964357706" v9="3615739378" v10="678276176" v11="276300178" v12="2734735973" v13="707690848" v14="557853201" v15="108009009">
                    <CSFeature sxBase="10" syBase="11" wBase="2" hBase="1" />
                </CSWeak>
                <CSWeak weigth="0.916748" v0="1346371584" v1="1074798594" v2="1903169539" v3="2021204512" v4="42" v5="540148256" v6="807403554" v7="15888482" v8="3296845677" v9="1082933252" v10="1414583617" v11="1161838775" v12="1117805" v13="1428521121" v14="1410679855" v15="1343247655">
                    <CSFeature sxBase="8" syBase="6" wBase="3" hBase="1" />
                </CSWeak>
                <CSWeak weigth="0.920111" v0="604254848" v1="1310730306" v2="1935804254" v3="1903194850" v4="269652554" v5="8970978" v6="1419968560" v7="81920608" v8="302072068" v9="1090519041" v10="1894868229" v11="33554947" v12="2173230871" v13="2292794629" v14="538117896" v15="364183559">
                    <CSFeature sxBase="5" syBase="9" wBase="5" hBase="1" />
                </CSWeak>
                <CSWeak weigth="0.911554" v0="839289456" v1="3473835722" v2="1984709026" v3="1188315744" v4="1076949489" v5="497052290" v6="62922849" v7="637469090" v8="1361101060" v9="47122432" v10="1133254404" v11="1317273605" v12="540729633" v13="2880381571" v14="103498298" v15="97255424">
                    <CSFeature sxBase="1" syBase="10" wBase="5" hBase="1" />
                </CSWeak>
                <CSWeak weigth="0.927574" v0="1529674474" v1="1458879416" v2="898274350" v3="3954258256" v4="3136897096" v5="3778958444" v6="283273619" v7="625291522" v8="1994949792" v9="4270111406" v10="1645870907" v11="362005640" v12="1654301486" v13="1091111049" v14="1079865625" v15="1679388977">
                    <CSFeature sxBase="2" syBase="1" wBase="3" hBase="1" />
                </CSWeak>
            </CSClassificator>
            <CSClassificator threshold="6.069467">
                <CSWeak weigth="1.038801" v0="1929433088" v1="268435584" v2="3489710208" v3="33554560" v4="436264960" v5="0" v6="1342177280" v7="0" v8="4194357312" v9="20480" v10="3087036416" v11="0" v12="704708416" v13="0" v14="973143586" v15="0">
                    <CSFeature sxBase="12" syBase="6" wBase="3" hBase="4" />
                </CSWeak>
                <CSWeak weigth="0.899740" v0="771751936" v1="8410240" v2="1128322496" v3="5440" v4="0" v5="0" v6="51401008" v7="12304" v8="4718608" v9="2164318208" v10="8389696" v11="17664" v12="8192" v13="128" v14="301989904" v15="0">
                    <CSFeature sxBase="12" syBase="12" wBase="3" hBase="2" />
                </CSWeak>
                <CSWeak weigth="0.848528" v0="603979776" v1="67108898" v2="1933180962" v3="1932657187" v4="133674" v5="1074790402" v6="3342370" v7="1932668966" v8="4245028689" v9="67371264" v10="1997657364" v11="335872017" v12="67239311" v13="2567" v14="278528" v15="1192251406">
                    <CSFeature sxBase="12" syBase="6" wBase="3" hBase="1" />
                </CSWeak>
                <CSWeak weigth="0.804712" v0="806373456" v1="2160066784" v2="1048797" v3="167780389" v4="1124758096" v5="2487228576" v6="1917060" v7="1310724" v8="607408248" v9="3232288908" v10="13107472" v11="270664373" v12="2801967361" v13="2896564385" v14="6" v15="54558720">
                    <CSFeature sxBase="13" syBase="17" wBase="2" hBase="1" />
                </CSWeak>
                <CSWeak weigth="0.823766" v0="101450248" v1="136884896" v2="13181056" v3="201416832" v4="159416320" v5="494931969" v6="1048652" v7="17039424" v8="3498071296" v9="279019908" v10="1481638946" v11="1377109681" v12="70340433" v13="1090716161" v14="1079333907" v15="1461523793">
                    <CSFeature sxBase="3" syBase="4" wBase="4" hBase="1" />
                </CSWeak>
                <CSWeak weigth="0.810021" v0="548436594" v1="339798096" v2="116671771" v3="1698186252" v4="1357443698" v5="9445490" v6="525667" v7="3281202" v8="982655504" v9="2326589092" v10="1442660757" v11="68683019" v12="1626972160" v13="1120460966" v14="537141266" v15="1572898">
                    <CSFeature sxBase="10" syBase="12" wBase="3" hBase="1" />
                </CSWeak>
                <CSWeak weigth="0.860355" v0="2181046818" v1="1075847712" v2="846349346" v3="3797942322" v4="572928546" v5="607674912" v6="2359328" v7="585375794" v8="4081311013" v9="1090519300" v10="1962891015" v11="8470786" v12="671092485" v13="268435721" v14="74793030" v15="68374807">
                    <CSFeature sxBase="6" syBase="6" wBase="5" hBase="1" />
                </CSWeak>
                <CSWeak weigth="0.823068" v0="1174452914" v1="1174422624" v2="1945503018" v3="1978405666" v4="3048469202" v5="680315618" v6="572654643" v7="552993842" v8="2021672269" v9="1327762432" v10="3623280965" v11="1262552322" v12="45635365" v13="244025601" v14="34022931" v15="352780331">
                    <CSFeature sxBase="3" syBase="9" wBase="5" hBase="1" />
                </CSWeak>
                <CSWeak weigth="0.800456" v0="1886404688" v1="276299888" v2="1345668407" v3="72877341" v4="274747504" v5="1082130512" v6="50480921" v7="1281" v8="2184212656" v9="3360161984" v10="7804277" v11="328969" v12="269488144" v13="8699904" v14="150994944" v15="0">
                    <CSFeature sxBase="12" syBase="14" wBase="3" hBase="1" />
                </CSWeak>
                <CSWeak weigth="0.827118" v0="1378897984" v1="103026768" v2="1124884652" v3="1352461967" v4="1718679410" v5="2244610" v6="272640039" v7="1582585137" v8="4037361266" v9="180261954" v10="39856264" v11="1342234625" v12="1984471155" v13="508429040" v14="1074989894" v15="47974002">
                    <CSFeature sxBase="11" syBase="11" wBase="2" hBase="1" />
                </CSWeak>
                <CSWeak weigth="0.781976" v0="1929433088" v1="33570880" v2="3506471040" v3="16777216" v4="453046272" v5="0" v6="8192" v7="0" v8="3120616512" v9="16793600" v10="554176512" v11="4096" v12="705194816" v13="0" v14="704670250" v15="4096">
                    <CSFeature sxBase="12" syBase="4" wBase="3" hBase="4" />
                </CSWeak>
                <CSWeak weigth="0.838665" v0="1647337680" v1="111952096" v2="100321172" v3="1413629833" v4="815984752" v5="111165536" v6="132931" v7="880" v8="3736760336" v9="3473600164" v10="478097688" v11="278678661" v12="993161297" v13="3606843616" v14="13313" v15="5247008">
                    <CSFeature sxBase="8" syBase="13" wBase="3" hBase="1" />
                </CSWeak>
                <CSWeak weigth="0.840352" v0="4246794866" v1="1185204778" v2="1973552040" v3="1693458208" v4="479912618" v5="3802292922" v6="570033162" v7="552477536" v8="1124226372" v9="67260167" v10="1884705613" v11="102762518" v12="716033941" v13="2374533388" v14="32649742" v15="1426329640">
                    <CSFeature sxBase="4" syBase="8" wBase="5" hBase="1" />
                </CSWeak>
                <CSWeak weigth="0.845648" v0="2791100658" v1="2697784517" v2="326238211" v3="2687664344" v4="2181583443" v5="2850422968" v6="3259589269" v7="17302272" v8="669356114" v9="4239196546" v10="2382430328" v11="2496193241" v12="180128051" v13="403296994" v14="2387674424" v15="12845656">
                    <CSFeature sxBase="14" syBase="18" wBase="1" hBase="1" />
                </CSWeak>
                <CSWeak weigth="0.799777" v0="1521758970" v1="1275896036" v2="1978970274" v3="3772192938" v4="1413044731" v5="615031490" v6="1879834841" v7="75374624" v8="3254998324" v9="184617542" v10="3227632989" v11="1078722562" v12="3140732196" v13="3163229441" v14="5186841" v15="81003045">
                    <CSFeature sxBase="3" syBase="10" wBase="5" hBase="1" />
                </CSWeak>
                <CSWeak weigth="0.814683" v0="1548501160" v1="357313684" v2="445120576" v3="86050048" v4="2099309804" v5="1426400976" v6="352641138" v7="822083840" v8="1074007168" v9="1896960180" v10="4219440" v11="1360073760" v12="148504578" v13="84042898" v14="339804214" v15="1118545">
                    <CSFeature sxBase="3" syBase="1" wBase="6" hBase="2" />
                </CSWeak>
                <CSWeak weigth="0.809324" v0="870060064" v1="1145209346" v2="2032297089" v3="1375795084" v4="1440248946" v5="1927942214" v6="1078214688" v7="1446265187" v8="1689221434" v9="512369248" v10="1349787687" v11="1368950020" v12="3928662190" v13="646054113" v14="535090" v15="14090450">
                    <CSFeature sxBase="10" syBase="10" wBase="2" hBase="1" />
                </CSWeak>
                <CSWeak weigth="0.854169" v0="547369712" v1="2394078912" v2="645501163" v3="1210067079" v4="4181721171" v5="4186623636" v6="2148602041" v7="2973806805" v8="2868927568" v9="3890364896" v10="132153560" v11="2798469256" v12="893390897" v13="4211247842" v14="554172672" v15="1073741952">
                    <CSFeature sxBase="18" syBase="18" wBase="1" hBase="1" />
                </CSWeak>
            </CSClassificator>
            <CSClassificator threshold="8.489312">
                <CSWeak weigth="0.873015" v0="10786" v1="1073752642" v2="872042291" v3="1926235938" v4="2237090" v5="573196962" v6="544875042" v7="855122466" v8="2668832064" v9="1059585" v10="2012706133" v11="273942784" v12="671629189" v13="134268329" v14="273155080" v15="285343780">
                    <CSFeature sxBase="9" syBase="9" wBase="4" hBase="1" />
                </CSWeak>
                <CSWeak weigth="0.790086" v0="2661071410" v1="3427333642" v2="1942357252" v3="3612820004" v4="4055825074" v5="2796202178" v6="27608254" v7="754384948" v8="4202751236" v9="3188105352" v10="3598406741" v11="1074528816" v12="784004397" v13="1253026177" v14="322319995" v15="1095106592">
                    <CSFeature sxBase="1" syBase="9" wBase="5" hBase="1" />
                </CSWeak>
                <CSWeak weigth="0.818929" v0="185105696" v1="1082183936" v2="318787712" v3="1342201856" v4="167796736" v5="2048" v6="285212672" v7="16777728" v8="2592" v9="8452672" v10="134244896" v11="45344" v12="134777354" v13="21042" v14="41002" v15="16">
                    <CSFeature sxBase="12" syBase="7" wBase="3" hBase="3" />
                </CSWeak>
                <CSWeak weigth="0.842369" v0="812671202" v1="1073763024" v2="654247225" v3="493765911" v4="3000021232" v5="8912960" v6="551437410" v7="792065" v8="1658774066" v9="3483165830" v10="2075857917" v11="1149046549" v12="309469234" v13="2476212578" v14="1712146" v15="1048608">
                    <CSFeature sxBase="10" syBase="13" wBase="3" hBase="1" />
                </CSWeak>
                <CSWeak weigth="0.849362" v0="3834135042" v1="3225946112" v2="3239067648" v3="3511702608" v4="17056" v5="2458194080" v6="605946200" v7="1400329042" v8="4237885407" v9="513594048" v10="3859060064" v11="357712240" v12="881724974" v13="1151087819" v14="38923810" v15="376640883">
                    <CSFeature sxBase="10" syBase="8" wBase="2" hBase="1" />
                </CSWeak>
                <CSWeak weigth="0.809122" v0="1621659650" v1="1081001098" v2="1733429124" v3="1417375648" v4="1219227770" v5="1011090114" v6="1423135856" v7="82838136" v8="2075917605" v9="1271694728" v10="96326617" v11="1484401922" v12="120991710" v13="112074912" v14="521949202" v15="105451628">
                    <CSFeature sxBase="7" syBase="10" wBase="3" hBase="1" />
                </CSWeak>
                <CSWeak weigth="0.818897" v0="1814591002" v1="675962522" v2="2007923624" v3="1979640546" v4="2820335242" v5="2324587106" v6="816455736" v7="1710100768" v8="2934068495" v9="67110916" v10="1945964886" v11="37957634" v12="3381326157" v13="1217956097" v14="62271247" v15="106299709">
                    <CSFeature sxBase="2" syBase="8" wBase="6" hBase="1" />
                </CSWeak>
                <CSWeak weigth="0.816658" v0="854638674" v1="39606856" v2="1903879298" v3="2113691395" v4="1919730292" v5="76296432" v6="808928930" v7="1911566690" v8="2958140448" v9="1595731423" v10="1465408405" v11="1496646612" v12="697648180" v13="223316451" v14="39329842" v15="309461152">
                    <CSFeature sxBase="9" syBase="11" wBase="3" hBase="1" />
                </CSWeak>
                <CSWeak weigth="0.844186" v0="170565666" v1="1147726368" v2="1894797314" v3="1357844576" v4="2357912098" v5="549382274" v6="564723754" v7="853935138" v8="3496762723" v9="1141114184" v10="3623351599" v11="1161826659" v12="11529701" v13="68781525" v14="276178438" v15="74256498">
                    <CSFeature sxBase="3" syBase="7" wBase="5" hBase="1" />
                </CSWeak>
                <CSWeak weigth="0.840316" v0="3551980074" v1="3265242423" v2="2654339569" v3="1173813404" v4="276081458" v5="2679716050" v6="2095752657" v7="1287949085" v8="1634888004" v9="3806633412" v10="2172891186" v11="2177859742" v12="462758019" v13="1940192285" v14="139082986" v15="309228404">
                    <CSFeature sxBase="9" syBase="18" wBase="1" hBase="1" />
                </CSWeak>
                <CSWeak weigth="0.850990" v0="2776693860" v1="1159249904" v2="597352124" v3="596372216" v4="2280958018" v5="3166486227" v6="2874118178" v7="106188961" v8="3887049378" v9="1160997381" v10="4129663781" v11="3485797079" v12="352114337" v13="1050938711" v14="387950352" v15="253576593">
                    <CSFeature sxBase="1" syBase="2" wBase="1" hBase="1" />
                </CSWeak>
                <CSWeak weigth="0.838522" v0="1811442290" v1="2994913336" v2="1325402281" v3="3666625669" v4="4739314" v5="293081168" v6="940630986" v7="1601649957" v8="3839372022" v9="1092437358" v10="100205803" v11="1413435551" v12="733159972" v13="187580608" v14="135797538" v15="41026162">
                    <CSFeature sxBase="12" syBase="11" wBase="2" hBase="1" />
                </CSWeak>
                <CSWeak weigth="0.852677" v0="1052770816" v1="1305538752" v2="582636578" v3="559944472" v4="34669344" v5="328033490" v6="1958152192" v7="824644002" v8="3306368385" v9="50414985" v10="1971279721" v11="17040430" v12="1409355577" v13="17913625" v14="425005061" v15="270270727">
                    <CSFeature sxBase="9" syBase="4" wBase="4" hBase="1" />
                </CSWeak>
                <CSWeak weigth="0.868980" v0="2524074554" v1="3389656168" v2="1189495960" v3="1819650944" v4="2955907168" v5="118227000" v6="207815363" v7="1380716786" v8="4226578353" v9="940371332" v10="2053068033" v11="1180388608" v12="2007642497" v13="1726808558" v14="302064710" v15="52178996">
                    <CSFeature sxBase="6" syBase="11" wBase="3" hBase="1" />
                </CSWeak>
                <CSWeak weigth="0.861466" v0="1109420658" v1="751062634" v2="4055523315" v3="3622584242" v4="3163037786" v5="581479138" v6="1630413490" v7="817766945" v8="168215808" v9="2390773504" v10="2379429135" v11="182846545" v12="61205836" v13="2351565569" v14="139799" v15="8593421">
                    <CSFeature sxBase="6" syBase="10" wBase="5" hBase="1" />
                </CSWeak>
                <CSWeak weigth="0.912298" v0="73449512" v1="3629051944" v2="1643155586" v3="4116031568" v4="2718465186" v5="517935298" v6="1849643170" v7="594813562" v8="1943645573" v9="3717367852" v10="1427174148" v11="1345671492" v12="2741741204" v13="1523485112" v14="1460932706" v15="1401312752">
                    <CSFeature sxBase="6" syBase="8" wBase="3" hBase="1" />
                </CSWeak>
                <CSWeak weigth="0.899256" v0="2993221162" v1="1014787748" v2="4133006688" v3="1384418088" v4="3439134728" v5="1953993776" v6="3380817432" v7="67441238" v8="143297064" v9="1354879722" v10="1075009745" v11="1394037014" v12="1246236689" v13="202612880" v14="1078153515" v15="391205157">
                    <CSFeature sxBase="1" syBase="3" wBase="3" hBase="1" />
                </CSWeak>
                <CSWeak weigth="0.897233" v0="3862169634" v1="1308623042" v2="1946814472" v3="1933608074" v4="3271086322" v5="32113252" v6="1084490242" v7="1381249906" v8="413596989" v9="2226033959" v10="2105888576" v11="479600959" v12="1776218057" v13="709529571" v14="386663014" v15="268764004">
                    <CSFeature sxBase="8" syBase="9" wBase="3" hBase="1" />
                </CSWeak>
                <CSWeak weigth="0.883880" v0="1452837474" v1="3423505482" v2="1708706224" v3="1969551922" v4="3084006113" v5="774695368" v6="3501416674" v7="15610165" v8="991730948" v9="2391574030" v10="190962253" v11="42467366" v12="883621237" v13="254779905" v14="1092056640" v15="117571590">
                    <CSFeature sxBase="2" syBase="10" wBase="5" hBase="1" />
                </CSWeak>
                <CSWeak weigth="0.870351" v0="1450462440" v1="3621020908" v2="400068168" v3="3862001107" v4="2336589384" v5="1361565898" v6="2466033078" v7="1065164979" v8="1868424328" v9="20852202" v10="521590376" v11="523862043" v12="1255769006" v13="1320132213" v14="207498159" v15="4284673">
                    <CSFeature sxBase="5" syBase="0" wBase="3" hBase="1" />
                </CSWeak>
                <CSWeak weigth="0.861613" v0="3489313522" v1="206967138" v2="1882359682" v3="1212608831" v4="1944049706" v5="1606344944" v6="733340615" v7="821204451" v8="3147702967" v9="721255038" v10="1014480701" v11="3023366000" v12="2511069805" v13="1370238863" v14="47524644" v15="352417288">
                    <CSFeature sxBase="0" syBase="0" wBase="2" hBase="1" />
                </CSWeak>
                <CSWeak weigth="0.874744" v0="2248286216" v1="1632653346" v2="1940525138" v3="857886754" v4="67109378" v5="5440034" v6="1110573159" v7="931332386" v8="3699425088" v9="710148097" v10="1463745536" v11="1346458708" v12="1107333071" v13="319107678" v14="285560860" v15="307318855">
                    <CSFeature sxBase="12" syBase="5" wBase="3" hBase="1" />
                </CSWeak>
            </CSClassificator>
        </TSCObjectDetector>
    </ILFObjectDetector>
</TLFDetectEngine>
